[{"twin": 1, "auxiliary": 1, "classifiers": 1, "gin": 1, "mingming": 1, "gong": 1, "13": 1, "": 6, "yanwu": 1, "xu": 1, "1": 2, "chunyuan": 1, "li2": 1, "kun": 1, "zhang3": 1, "kayhan": 1, "batmanghelich1": 1, "department": 2, "biomedical": 1, "informatics": 1, "university": 2, "pittsburgh": 1, "mig73yanwuxukayhanpittedu": 1, "2": 1, "microsoft": 1, "research": 1, "redmond": 1, "cl319dukeedu": 1, "3": 1, "philosophy": 1, "carnegie": 1, "mellon": 1, "kunz1cmuedu": 1, "abstract": 1, "conditional": 1, "generative": 1, "model": 1, "enjoy": 1, "remarkable": 1, "progress": 1, "past": 1, "years": 1}, {"one": 1, "popular": 1, "conditional": 1, "model": 1, "auxiliary": 2, "classifier": 2, "gin": 2, "acgan": 1, "generate": 1, "highly": 1, "discriminative": 1, "image": 1, "extend": 1, "loss": 1, "function": 1}, {"however": 1, "diversity": 1, "generate": 1, "sample": 1, "acgan": 1, "tend": 1, "decrease": 1, "number": 1, "class": 1, "increase": 1, "hence": 1, "limit": 1, "power": 1, "largescale": 1, "data": 1}, {"paper": 1, "identify": 1, "source": 1, "low": 1, "diversity": 1, "issue": 1, "theoretically": 1, "propose": 1, "practical": 1, "solution": 1, "solve": 1, "problem": 1}, {"show": 1, "auxiliary": 1, "classifier": 1, "acgan": 1, "impose": 1, "perfect": 1, "separability": 1, "disadvantageous": 1, "support": 1, "class": 1, "distributions": 1, "significant": 1, "overlap": 1}, {"address": 1, "issue": 1, "propose": 1, "twin": 1, "auxiliary": 1, "classifiers": 1, "generative": 1, "adversarial": 1, "net": 1, "tacgan": 1, "benefit": 1, "new": 1, "player": 1, "interact": 1, "players": 1, "generator": 1, "discriminator": 1, "gin": 1}, {"theoretically": 1, "demonstrate": 1, "tacgan": 1, "effectively": 1, "minimize": 1, "divergence": 1, "generate": 1, "realdata": 1, "distributions": 1}, {"extensive": 1, "experimental": 1, "result": 1, "show": 1, "tacgan": 1, "successfully": 1, "replicate": 1, "true": 1, "data": 2, "distributions": 1, "simulate": 1, "significantly": 1, "improve": 1, "diversity": 1, "classconditional": 1, "image": 1, "generation": 1, "real": 1, "datasets": 1}, {"1": 2, "": 2, "introduction": 1, "generative": 1, "adversarial": 1, "network": 1, "gans": 1, "framework": 1, "learn": 1, "data": 1, "generate": 1, "distribution": 1, "implicitly": 1}, {"gans": 1, "mimic": 1, "sample": 2, "target": 1, "distribution": 2, "train": 1, "generator": 1, "map": 1, "draw": 1, "canonical": 1, "data": 1, "space": 1}, {"distinctive": 1, "feature": 1, "gans": 1, "discriminator": 1, "evaluate": 1, "separability": 1, "real": 1, "generate": 1, "data": 1, "distributions": 1, "14": 1}, {"discriminator": 1, "hardly": 1, "distinguish": 1, "real": 1, "generate": 1, "data": 2, "generator": 1, "likely": 1, "provide": 1, "good": 1, "approximation": 1, "true": 1, "distribution": 1}, {"generate": 1, "highfidelity": 1, "image": 1, "much": 1, "recent": 1, "research": 1, "focus": 1, "design": 1, "advance": 1, "network": 1, "architectures": 1, "5": 1, "6": 1, "develop": 1, "stable": 1, "objective": 1, "function": 1, "79": 1, "3": 1, "enforce": 1, "appropriate": 1, "constraints": 1, "discriminator": 1, "1012": 1, "improve": 1, "train": 1, "techniques": 1, "7": 1, "13": 1}, {"conditional": 1, "gans": 2, "cgans": 1, "14": 1, "variant": 1, "take": 1, "advantage": 1, "extra": 1, "information": 1, "condition": 1, "widely": 1, "use": 1, "generation": 1, "classconditioned": 1, "image": 1, "1518": 1, "text": 1, "19": 1, "20": 1}, {"major": 1, "difference": 1, "cgans": 2, "gans": 1, "fee": 1, "condition": 2, "generator": 1, "discriminator": 1, "lean": 1, "joint": 1, "distributions": 1, "image": 1, "random": 1, "variables": 1}, {"methods": 1, "fee": 1, "conditional": 1, "information": 1, "concatenate": 1, "embed": 1, "input": 1, "feature": 1, "vector": 1, "specific": 1, "layer": 1, "14": 1, "21": 1, "15": 1, "22": 1, "23": 1, "20": 1}, {"recently": 1, "projectioncgan": 1, "24": 1, "improve": 1, "quality": 1, "generate": 1, "image": 1, "use": 1, "specific": 1, "discriminator": 1, "take": 1, "inner": 1, "product": 1, "embed": 1, "condition": 1, "variable": 1, "feature": 1, "vector": 1, "input": 1, "": 1}, {"equal": 1, "contribution": 1, "code": 1, "available": 1, "httpsgithubcombatmanlabtwinac": 1}, {"33rd": 1, "conference": 1, "neural": 1, "information": 1, "process": 1, "systems": 1, "neurips": 1, "2019": 1, "vancouver": 1, "canada": 1}, {"image": 2, "obtain": 1, "stateoftheart": 1, "classconditional": 1, "generation": 1, "largescale": 1, "datasets": 1, "imagenet1000": 1, "25": 1}, {"among": 1, "cgans": 1, "auxiliary": 1, "classifier": 1, "gin": 1, "acgan": 1, "receive": 1, "much": 1, "attention": 1, "due": 1, "simplicity": 1, "extensibility": 1, "various": 1, "applications": 1, "17": 1}, {"acgan": 1, "incorporate": 1, "conditional": 1, "information": 1, "label": 1, "train": 1, "gin": 1, "discriminator": 1, "additional": 1, "classification": 1, "loss": 1}, {"acgan": 1, "able": 1, "generate": 1, "highquality": 1, "image": 1, "extend": 1, "various": 1, "learn": 1, "problems": 1, "texttoimage": 1, "generation": 1, "26": 1}, {"however": 1, "report": 1, "literature": 1, "17": 1, "24": 1, "number": 1, "label": 1, "increase": 1, "acgan": 1, "tend": 1, "generate": 1, "nearidentical": 1, "image": 1, "class": 1}, {"miyato": 1, "et": 1, "al": 1}, {"24": 1, "observe": 1, "phenomenon": 1, "imagenet1000": 1, "conjecture": 1, "auxiliary": 1, "classifier": 1, "might": 1, "encourage": 1, "generator": 1, "produce": 1, "less": 1, "diverse": 1, "image": 1, "easily": 1, "discernable": 1}, {"despite": 1, "insightful": 1, "find": 1, "exact": 1, "source": 1, "lowdiversity": 1, "problem": 1, "unclear": 1, "let": 1, "alone": 1, "remedy": 1}, {"paper": 1, "aim": 1, "provide": 1, "understand": 1, "phenomenon": 1, "accordingly": 1, "develop": 1, "new": 1, "method": 1, "able": 1, "generate": 1, "diverse": 1, "realistic": 1, "image": 1}, {"first": 1, "show": 1, "due": 1, "miss": 1, "term": 1, "objective": 1, "acgan": 1, "faithfully": 1, "minimize": 1, "divergence": 1, "real": 1, "generate": 1, "conditional": 1, "distribution": 1}, {"show": 1, "miss": 1, "term": 1, "result": 1, "degenerate": 1, "solution": 1, "explain": 1, "lack": 1, "diversity": 1, "generate": 1, "data": 1}, {"base": 1, "understand": 1, "introduce": 1, "new": 1, "player": 1, "minmax": 1, "game": 1, "acgan": 1, "enable": 1, "us": 1, "estimate": 1, "miss": 1, "term": 1, "objective": 1}, {"result": 1, "method": 1, "properly": 1, "estimate": 1, "divergence": 1, "real": 1, "generate": 1, "conditional": 1, "distributions": 1, "significantly": 1, "increase": 1, "sample": 1, "diversity": 1, "within": 1, "class": 1}, {"call": 1, "method": 1, "twin": 1, "auxiliary": 1, "classifiers": 1, "gin": 1, "tacgan": 1, "since": 1, "new": 1, "player": 1, "also": 1, "classifier": 1}, {"compare": 1, "acgan": 1, "tacgan": 1, "successfully": 1, "replicate": 1, "real": 1, "data": 2, "distributions": 1, "simulate": 1, "significantly": 1, "improve": 1, "quality": 1, "diversity": 1, "classconditional": 1, "image": 1, "generation": 1, "cifar100": 1, "27": 1, "vggface2": 1, "28": 1, "imagenet1000": 1, "25": 1, "datasets": 1}, {"particular": 1, "best": 1, "knowledge": 1, "tacgan": 2, "first": 1, "cgan": 1, "method": 1, "generate": 1, "good": 1, "quality": 1, "image": 1, "vggface": 1, "dataset": 1, "demonstrate": 1, "advantage": 1, "finegrained": 1, "datasets": 1}, {"2": 1, "": 2, "method": 1, "section": 1, "review": 1, "generative": 1, "adversarial": 1, "network": 1, "gin": 1, "1": 1, "conditional": 1, "variant": 1, "cgan": 1, "14": 1}, {"review": 1, "one": 1, "popular": 1, "variants": 1, "cgan": 1, "call": 1, "auxiliary": 1, "classifier": 1, "gin": 1, "acgan": 1, "17": 1}, {"first": 1, "provide": 1, "understand": 1, "observation": 1, "lowdiversity": 1, "sample": 1, "generate": 1, "acgan": 1, "distribution": 1, "match": 1, "perspective": 1}, {"second": 1, "base": 1, "new": 2, "understand": 1, "problem": 1, "propose": 1, "method": 1, "enable": 1, "learn": 1, "real": 1, "distributions": 1, "increase": 1, "sample": 1, "diversity": 1}, {"21": 1, "": 4, "background": 1, "give": 1, "train": 1, "set": 1, "xi": 1, "ni1": 1, "x": 1, "draw": 1, "unknown": 1, "distribution": 2, "px": 2, "gin": 1, "estimate": 1, "specify": 1, "qx": 1, "implicitly": 1}, {"instead": 1, "explicit": 1, "parametrization": 1, "train": 2, "generator": 1, "function": 1, "gz": 1, "map": 1, "sample": 1, "canonical": 1, "distribution": 1, "ie": 1, "z": 1, "": 2, "pz": 1, "data": 1}, {"generator": 1, "obtain": 1, "find": 1, "equilibrium": 1, "follow": 1, "minimax": 1, "game": 1, "effectively": 1, "minimize": 1, "jensenshannon": 1, "divergence": 1, "jsd": 1, "qx": 1, "px": 1, "": 8, "min": 1, "max": 1, "e": 2, "log": 1, "dx": 1, "g": 1, "xpx": 1, "log1": 1, "dgz": 1, "zpz": 1, "1": 1, "discriminator": 1}, {"notice": 1, "qx": 1, "directly": 1, "model": 1}, {"give": 1, "pair": 1, "observation": 1, "x": 2, "condition": 1, "xi": 2, "": 7, "yni1": 1, "draw": 1, "joint": 1, "distribution": 2, "pxy": 2, "goal": 1, "cgan": 1, "estimate": 1, "conditional": 1}, {"let": 1, "qxy": 3, "denote": 1, "conditional": 1, "distribution": 1, "specify": 1, "generator": 1, "gy": 1, "z": 1, "": 2, "py": 1}, {"generic": 1, "cgan": 1, "train": 1, "g": 2, "implicitly": 1, "minimize": 1, "jsd": 1, "divergence": 1, "joint": 1, "distributions": 1, "qxy": 1, "pxy": 2, "": 12, "min": 1, "max": 1, "e": 2, "xy": 1, "log": 1, "dx": 1, "zpz": 1, "py": 1, "log1": 1, "dgz": 1}, {"2": 1, "": 1, "general": 1, "continuous": 1, "discrete": 1, "variable": 1}, {"paper": 1, "focus": 1, "case": 1, "discrete": 1, "class": 1, "label": 1, "ie": 1, "": 2, "1": 1}, {"": 1}, {"": 1}, {"": 1, "k": 1}, {"2": 1, "": 3, "22": 1, "insight": 1, "auxiliary": 1, "classifier": 2, "gin": 1, "acgan": 2, "introduce": 1, "new": 1, "player": 1, "c": 1, "interact": 1, "g": 1, "players": 1}, {"use": 1, "qcy": 1, "x": 1, "denote": 1, "conditional": 1, "distribution": 1, "induce": 1, "c": 5, "acgan": 1, "optimization": 1, "combine": 1, "original": 1, "gin": 2, "loss": 2, "crossentropy": 1, "classification": 2, "min": 1, "max": 1, "lac": 1, "g": 1, "dc": 1, "": 27, "gc": 1, "e": 4, "log": 2, "dx": 1, "xpx": 1, "z": 3, "zpz": 2, "py": 2, "xy": 1, "pxy": 1, "log1": 1, "dgz": 1, "cx": 1, "logcgz": 1, "3": 1, "b": 1, "hyperparameter": 1, "balance": 1, "auxiliary": 1, "losses": 1}, {"decompose": 1, "objective": 1, "acgan": 1, "three": 1, "term": 1}, {"clearly": 1, "first": 1, "term": 1, "correspond": 1, "jensenshannon": 1, "divergence": 1, "jsd": 1, "qx": 1, "px": 1, "": 1}, {"second": 1, "term": 1, "b": 1, "crossentropy": 1, "loss": 1, "real": 1, "data": 1}, {"straightforward": 1, "show": 2, "second": 1, "term": 1, "minimize": 1, "kullbackleibler": 1, "kl": 1, "divergence": 1, "real": 1, "data": 1, "distribution": 2, "py": 1, "x": 11, "qcy": 2, "specify": 1, "c": 2, "add": 1, "negative": 1, "conditional": 1, "entropy": 1, "hp": 2, "": 19, "exy": 1, "pxy": 4, "log": 6, "p": 4, "b": 2, "e": 4, "xy": 3, "cx": 1, "qc": 1, "klpy": 1}, {"q": 1, "x": 2, "xy": 2, "pxy": 2, "": 5, "e": 1, "4": 1, "since": 1, "negative": 1, "conditional": 1, "entropy": 1, "hp": 1, "constant": 1, "term": 1, "minimize": 1, "b": 1, "wrt": 1}, {"network": 1, "parameters": 1, "c": 1, "effectively": 1, "minimize": 1, "kl": 1, "divergence": 1, "py": 1, "x": 2, "qcy": 1, "": 1}, {"third": 1, "term": 1, "c": 1, "crossentropy": 1, "loss": 1, "generate": 1, "data": 1}, {"similarly": 1, "one": 1, "add": 1, "negative": 1, "entropy": 1, "hq": 2, "x": 7, "": 12, "exy": 1, "qxy": 3, "log": 3, "qy": 2, "c": 2, "obtain": 1, "follow": 1, "result": 1, "e": 2, "xy": 2, "qc": 1, "klqy": 1, "qcy": 1}, {"update": 1, "c": 2, "hq": 1, "x": 1, "consider": 1, "constant": 1, "term": 1, "thus": 1, "minimize": 1, "wrt": 1}, {"c": 1, "effectively": 1, "minimize": 1, "kl": 1, "divergence": 1, "qy": 1, "x": 2, "qcy": 1, "": 1}, {"however": 1, "update": 2, "g": 3, "hq": 2, "x": 5, "cannot": 1, "consider": 1, "constant": 1, "term": 1, "qy": 2, "conditional": 1, "distribution": 1, "specify": 1, "generator": 1, "acgan": 1, "ignore": 1, "minimize": 2, "c": 1, "optimization": 1, "procedure": 1, "fail": 1, "kl": 1, "divergence": 1, "qcy": 1, "": 1}, {"hypothesize": 1, "likely": 1, "reason": 1, "behind": 1, "low": 1, "diversity": 1, "sample": 1, "generate": 1, "acgan": 2, "fail": 1, "account": 1, "miss": 1, "term": 1, "update": 1, "g": 1, "fact": 1, "follow": 1, "theorem": 2, "show": 1, "converge": 1, "degenerate": 1, "distribution": 1, "1": 1}, {"suppose": 1, "px": 1, "": 2, "qx": 1}, {"give": 1, "auxiliary": 1, "classifier": 1, "c": 2, "specify": 1, "conditional": 2, "distribution": 2, "qcy": 1, "x": 4, "": 8, "optimal": 1, "g": 1, "minimize": 1, "induce": 1, "follow": 1, "degenerate": 1, "qy": 1, "1": 1, "karg": 1, "maxi": 1, "qc": 1, "ix": 1, "q": 1, "kx": 1, "5": 1, "0": 1, "otherwise": 1}, {"proof": 1, "give": 1, "section": 1, "s1": 1, "supplementary": 1, "material": 1, "sm": 1}, {"theorem": 1, "1": 1, "show": 1, "even": 1, "marginal": 1, "distributions": 2, "perfectly": 1, "match": 1, "gin": 1, "loss": 1, "": 1, "acgan": 1, "able": 1, "model": 1, "probability": 1, "class": 1, "support": 1, "overlap": 1}, {"tend": 1, "generate": 1, "data": 1, "deterministically": 1, "relate": 1, "x": 1}, {"mean": 1, "generate": 1, "image": 1, "class": 2, "confine": 1, "regions": 1, "induce": 1, "decision": 1, "boundaries": 1, "auxiliary": 1, "classifier": 1, "c": 2, "fail": 1, "replicate": 1, "conditional": 1, "distribution": 1, "qcy": 1, "x": 1, "": 1, "imply": 1, "reduce": 1, "distributional": 1, "support": 1}, {"theoretical": 1, "result": 2, "consistent": 1, "empirical": 1, "24": 1, "acgan": 1, "generate": 1, "discriminable": 1, "image": 1, "low": 1, "intraclass": 1, "diversity": 1}, {"thus": 1, "essential": 1, "incorporate": 1, "miss": 1, "term": 1, "hq": 1, "x": 3, "objective": 1, "penalize": 1, "behavior": 1, "minimize": 1, "kl": 1, "divergence": 1, "qy": 1, "qcy": 1, "": 1}, {"3": 1, "": 21, "generator": 1, "g": 1, "auxiliary": 2, "c": 2, "latexit": 21, "sha1base64tujve4wkwrlcvixrgxzqpzwag8aaab6hicbvbns8naej3ur1qqh69lbbbu0le0gprgx5bsbqhrlzttq1m03y3qgl9bd48aciv3snn2zyhbx0w8hhvhpl5qsk4nq777rtw1jc2t4rbpz3dvf2d8ufrs8epythksyhvj6aabzfynnwi7cqkarqibafj25nffkkleswfzcrbp6jdyupoqlfs465frrhvdw6ysrycvcbhvv6g1ilkyodrnu667njsbpqdkcczyweqnghlixhwlxukkj1h42p3rkzqwyiggsbeld5urviyxgwkiwhzg1iz0sjcto6qqmvyzljduo2wjrmapiyjl7mgy4qmbexblkfle3ejaiijjjsynzelzll1dj66lquvwvcvmp3erxfoeetuecplicgtxdhzraaoezxuhnexrenhfny9facpkzygd5mhmwmywlatexit": 1, "inputlabel": 3, "sha1base649k1jv5arfanoalxd7nefzrfucaaab6hicbvbns8naej3ur1qqh69lbbbu0le0goxf48t2a9oq9lsj3azsbsboqsgu8efdeqzjmgbzudtj4yelw3w8y8ibfcg9f9dgobm1vbo8xd0t7wefrfikrenumwyxwmsqg1cngktsgw4edhofnaoedojjfe53nlbphsshm03qjhi8pazaqzurakfbfqlkdwizetcurodmpfwhm0gilyyjq3fpcxpgzvyyzgbnsp9wyudahixzkmme2s8wh87ihvwgjiyvlwniqv09kdfi62ku2m6imrfe9ebif14vnegtn3gzpaylwy4ku0fmtozfkyfxyiyywkkz4vzwwszuuwzsniubgrf68jppx1u9to1ryu1uzyoipzbovycbzdqg3toqasyidzdk7w5j86l858lfsltj5zcngfp4alewmxwlatexit": 1, "noise": 1, "z": 1, "reallabel": 1, "sha1base64gvcmqvlue25tqa0uw4ycpnbw1rqaaab6hicbvbns8naej3ur1qqh69lbbbu0le0gpri8cw7ae2owy2k3btzhn2n0ijqvepcji1zkzxjts1bwx8mpn6bywzekaiujeto4w19y3nrej2awd3bgfhju0ngqgdzzlglvcahgwsu2dtcco4lcgguc28h4dua3n1bphst7m0nqjhq8pazaqzueoixk27vnyosei8nfchr75eeooyprfkwwtvuuu5ifezqgxnaqelxqoxowxmh9i1vniitznd52sm6smsbgrw9kqufp7iqor1pmosj0rnso97m3e7xuasjrpmysq1ktlgupokymmyjgoukbkxsyqyxe2thi2ooszybeo2bg55vxsuqh6btvrxfzqn3kcrtibuzghd66gbndqhyywqhigv3hzhp0x5935wlqwnhzmgp7afwbumgm3glatexit": 1, "sha1base64t3f5yatjwewlpp50x1bs1vdmuc0aaab6hicbvbns8naej3ur1qqh69lbbbu0le0gpri8cw7ie0owy2k3btzhn2n0ijqvepcji1zkzxjts1bwx8mpn6bywzekaiujeto4w19y3nrej2awd3bgfhju0ngqgdzzlglvcahgwsu2dtcco4lcgguc28h4dua3n1bphst7m0nqjhq8pazaqzueoixk27vnyosei8nfchr75eeooyprfkwwtvuuu5ifezqgxnaqelxqoxowxmh9i1vniitznd52sm6smsbgrw9kqufp7iqor1pmosj0rnso97m3e7xuasjrpmysq1ktlgupokymmyjgoukbkxsyqyxe2thi2ooszybeo2bg55vxsuqh6btvrxfzqn3kcrtibuzghd66gbndqhyywqhigv3hzhp0x5935wlqwnhzmgp7afwbtz2m3qlatexit": 4, "fake": 1, "real": 1, "x": 2, "sha1base64hf6hoetjsel13izimoptay5eaaab6hicbvbns8naej3ur1qqh69lbbbu0leqmeif48t2a9oq9lsj3azsbsboqsgu8efdeqzjmgbzudtj4yelw3w8y8ibfcg9f9dgobm1vbo8xd0t7wefrfikrenumwyxwmsqg1cngktsgw4edhofnaoedolj3dzvpkhspjypzpqgh9gr5cfn1fip2r2uk27vxycsey8nfcjrgjssoyprfkwwtvuue5ifezqgxnamelfqoxowxcr9izvniitz8tdp2rc6smsrgrw9kqhfp7iqor1tmosj0rnwo96s3f7xeasibpmysq1ktlwupokymmyjkoukbkxtyqyxe2thi2poszybeo2bg15xxsvqp6btvrxlfqt3kcrtidc7ged2pqh3toqasyidzdk7w5j86l858lfsltj5zcngfp4atbmm3alatexit": 2, "realfake": 1, "twin": 1, "mi": 1, "discriminator": 1, "sha1base64nslos3law3wlkybc0euhsysjs0aaab6hicbvbns8naej3ur1qqh69lbbbu0le0gnrdx5bsbqhrlzttq1m03y3qgl9bd48aciv3snn2zyhbx0w8hhvhpl5qsk4nq777rtw1jc2t4rbpz3dvf2d8ufrs8epythksyhvj6aabzfynnwi7cqkarqibafj25nffkkleswfzcrbp6jdyupoqlfs465frrhvdw6ysrycvcbhvv6g1ilkyodrnu667njsbpqdkcczyweqnghlixhwlxukkj1h42p3rkzqwyiggsbeld5urviyxgwkiwhzg1iz0sjcto6qqmvyzljduo2wjrmapiyjl7mgy4qmbexblkfle3ejaiijjjsynzelzll1dj66lquvwvcvmp3erxfoeetuecplicgtxdhzraaoezxuhnexrenhfny9facpkzygd5mhl2mmyalatexit": 1, "sha1base64xznwmxzxhygeidgchcttq5dowaaab7xicbvdlsgnbeoynrxhfuy9ebopgkeykomdglh4jmacka5idzczj5rhmzaphyt948acivhm3jjnmdjhy0ffxddhdfcwfgv63v1hb39jckm6xdnb39gkh0cto1jnajmornqnwozyjmntmstpj9eui4jtdjsuzz2e9wgkxlvjwknbr5kfjocrzna9ydmsgmxpgrhxolqq5qucorr81rsokgoqlehymg7gjzbmslamcdot9vjde0zgeei7jkosqamzbvtdoauayqvdiutmqujzisjjmiyhukbedm2zuj3nd1mbxyczkkloqywjrnhjkfzq9jgzmu2l5xbfmnho3ijlcghpraiq5eilll1dj66ianxg7rjsu8njkmijnmi5bhafnbifbjsbwcm8wyu8ecp78d69j0vrwctnjuepvm8fntspjqlatexit": 1, "figure": 1, "1": 1, "illustration": 1, "propose": 1, "tacgan": 1}, {"generator": 1, "g": 1, "synthesize": 1, "fake": 1, "sample": 1, "x": 1, "condition": 1, "input": 1, "label": 1, "": 1}, {"discriminator": 1, "distinguish": 1, "realfake": 1, "sample": 1}, {"auxiliary": 2, "classifier": 2, "c": 2, "train": 2, "classify": 1, "label": 1, "real": 1, "fake": 2, "pair": 2, "propose": 1, "twin": 1, "mi": 1}, {"23": 1, "": 2, "twin": 1, "auxiliary": 1, "classifiers": 1, "gin": 1, "tacgan": 1, "analysis": 1, "previous": 1, "section": 1, "motivate": 1, "add": 1, "miss": 1, "term": 1, "hq": 1, "x": 1, "back": 1, "objective": 1, "function": 1}, {"minimize": 1, "c": 1, "force": 1, "g": 1, "concentrate": 1, "conditional": 1, "density": 1, "mass": 1, "train": 1, "data": 1, "hq": 1, "x": 1, "work": 1, "opposite": 1, "direction": 1, "increase": 1, "entropy": 1}, {"however": 1, "estimate": 1, "hq": 1, "x": 2, "challenge": 1, "task": 1, "since": 1, "access": 1, "qy": 1, "": 1}, {"various": 1, "methods": 1, "propose": 1, "estimate": 1, "conditional": 1, "entropy": 1, "2932": 1, "however": 1, "estimators": 1, "cannot": 1, "easily": 1, "use": 1, "objective": 1, "function": 1, "learn": 1, "g": 1, "via": 1, "backpropagation": 1}, {"propose": 1, "estimate": 1, "conditional": 1, "entropy": 1, "add": 1, "new": 1, "player": 1, "minimax": 1, "game": 1}, {"general": 1, "idea": 1, "introduce": 1, "additional": 1, "auxiliary": 1, "classifier": 1, "c": 2, "mi": 2, "": 3, "aim": 1, "identify": 1, "label": 1, "sample": 1, "draw": 1, "qxy": 1, "lowdiversity": 1, "case": 1, "make": 1, "task": 1, "easy": 1}, {"similar": 1, "gin": 1, "generator": 1, "try": 1, "compete": 1, "c": 1, "mi": 1, "": 1}, {"overall": 1, "idea": 1, "tacgan": 1, "illustrate": 1, "figure": 1, "1": 1}, {"follow": 1, "demonstrate": 1, "connection": 1, "minimize": 1, "hq": 1, "x": 1}, {"proposition": 1, "let": 1, "us": 1, "assume": 1, "without": 1, "loss": 1, "generality": 1, "class": 1, "equally": 1, "likely": 1, "1": 2, "ie": 1, "p": 1, "": 3, "k": 2}, {"minimize": 2, "hq": 1, "x": 2, "equivalent": 1, "1": 2, "mutual": 1, "information": 1, "2": 1, "jsd": 1, "conditional": 1, "distributions": 1, "qxy": 1, "": 2}, {"": 1}, {"": 1}, {"": 2, "qxy": 1, "k": 1}, {"proof": 1}, {"iq": 1, "x": 6, "": 17, "hy": 1, "hq": 3, "xy": 1, "k": 9, "1": 4, "e": 2, "log": 2, "qx": 2, "qxy": 1, "xqxy": 2, "k1": 2, "klqxy": 1, "jsdqxy": 1}, {"": 1}, {"": 1}, {"": 2, "qxy": 1, "k": 1}, {"k": 1, "": 3, "6": 1, "k1": 1, "1": 1, "follow": 1, "fact": 1, "entropy": 1, "constant": 1, "respect": 1, "q": 1, "2": 1, "show": 1}, {"base": 1, "connection": 1, "hq": 1, "x": 1, "jsd": 2, "extend": 1, "twoplayer": 1, "minimax": 1, "approach": 1, "gin": 1, "1": 1, "minimize": 1, "multiple": 1, "distributions": 1}, {"specifically": 1, "use": 1, "another": 1, "auxiliary": 1, "classifier": 1, "c": 3, "mi": 4, "whose": 1, "last": 1, "layer": 1, "softmax": 1, "function": 1, "predict": 1, "probability": 1, "x": 1, "belong": 1, "class": 1, "": 9, "k": 1, "define": 1, "follow": 1, "minimax": 1, "game": 1, "min": 1, "max": 1, "v": 1, "g": 2, "e": 1, "zpz": 1, "py": 1, "logc": 1, "gz": 1}, {"7": 1, "": 3, "follow": 1, "theorem": 1, "show": 1, "minimax": 1, "game": 1, "effectively": 1, "minimize": 1, "jsd": 1, "qxy": 1, "1": 1}, {"": 1}, {"": 1}, {"": 2, "qxy": 1, "k": 1}, {"theorem": 1, "2": 1}, {"let": 1, "u": 1, "g": 2, "": 2, "max": 1, "v": 1, "c": 1, "mi": 1}, {"global": 1, "mininum": 1, "minimax": 1, "game": 1, "achieve": 1, "mi": 1, "c": 1, "": 8, "qxy": 3, "1": 1, "2": 1, "k": 1}, {"optimal": 1, "point": 1, "u": 1, "g": 1, "achieve": 1, "value": 1, "k": 2, "log": 1, "1": 1, "": 1, "dataset": 1, "imbalanced": 1, "apply": 1, "bias": 1, "batch": 1, "sample": 1, "enforce": 1, "condition": 1}, {"4": 1, "": 1, "complete": 1, "proof": 1, "theorem": 1, "2": 1, "give": 1, "section": 1, "s2": 1, "sm": 1}, {"worth": 1, "note": 1, "global": 1, "optimum": 1, "u": 1, "g": 4, "cannot": 1, "achieve": 1, "model": 1, "term": 1, "tacgan": 1, "objective": 2, "function": 1, "obtain": 1, "comb": 1, "7": 1, "original": 1, "acgan": 1, "3": 1, "min": 1, "max": 1, "ltac": 1, "c": 5, "mi": 2, "": 4, "lac": 1, "v": 1}, {"mi": 1, "gc": 1, "dc": 1, "": 3, "8": 1, "follow": 1, "theorem": 1, "provide": 1, "approximation": 1, "guarantee": 1, "joint": 1, "distribution": 1, "pxy": 1, "justify": 1, "validity": 1, "propose": 1, "approach": 1}, {"theorem": 1, "3": 1}, {"let": 1, "py": 1, "x": 2, "qy": 1, "denote": 1, "data": 1, "distribution": 2, "specify": 1, "generator": 1, "g": 1, "respectively": 1}, {"let": 1, "qcy": 3, "x": 7, "denote": 1, "conditional": 1, "distribution": 1, "give": 1, "specify": 1, "auxiliary": 1, "classifier": 1, "c": 1, "q": 2, "p": 1, "jsdpxy": 1, "": 10, "qxy": 1, "2c1": 1, "2jsdpx": 1, "qx": 2, "c2": 3, "2klpy": 1, "2klqy": 1, "r": 2, "c1": 1, "upper": 1, "bound": 1, "12": 2, "py": 1, "yxx": 1, "xx": 1, "finite": 1, "measure": 1, "respectively": 1}, {"proof": 1, "theorem": 1, "3": 1, "provide": 1, "section": 1, "s3": 1, "sm": 1}, {"3": 1, "": 2, "relate": 1, "work": 1, "tacgan": 1, "learn": 1, "unbiased": 1, "distribution": 1}, {"shu": 1, "et": 1, "al": 1}, {"33": 1, "first": 1, "show": 1, "acgan": 1, "tend": 1, "downsample": 1, "data": 1, "point": 1, "near": 1, "decision": 1, "boundary": 1, "cause": 1, "bias": 1, "estimation": 1, "true": 1, "distribution": 1}, {"lagrangian": 1, "perspective": 1, "consider": 1, "acgan": 1, "minimize": 1, "jsdpx": 1, "": 2, "qx": 1, "constraints": 1, "enforce": 1, "classification": 1, "losses": 1}, {"c": 1, "large": 1, "jsdpx": 1, "": 2, "qx": 1, "become": 1, "less": 1, "effective": 1, "generator": 1, "push": 1, "generate": 1, "image": 1, "away": 1, "boundary": 1}, {"however": 1, "real": 1, "datasets": 1, "also": 1, "observe": 1, "low": 1, "diversity": 1, "c": 1, "small": 1, "cannot": 1, "explain": 1, "analysis": 1, "33": 1}, {"take": 1, "different": 1, "perspective": 1, "constrain": 1, "jsdpx": 1, "": 3, "qx": 1, "small": 1, "investigate": 1, "properties": 1, "conditional": 1, "qy": 1, "x": 1}, {"analysis": 1, "suggest": 1, "even": 1, "jsdpx": 1, "": 4, "qx": 1, "0": 1, "acgan": 1, "crossentropy": 1, "loss": 1, "still": 1, "result": 1, "bias": 1, "estimate": 1, "qy": 1, "x": 1, "reduce": 1, "support": 1, "class": 1, "generate": 1, "distribution": 2, "compare": 1, "true": 1}, {"furthermore": 1, "propose": 1, "solution": 1, "remedy": 1, "low": 1, "diversity": 1, "problem": 1, "base": 1, "understand": 1}, {"connect": 1, "tacgan": 1, "projection": 1, "cgan": 1}, {"acgan": 1, "stateoftheart": 1, "method": 1, "advent": 1, "projection": 1, "cgan": 1, "24": 1}, {"projection": 1, "cgan": 1, "acgan": 1, "tacgan": 1, "share": 1, "similar": 1, "spirit": 1, "image": 1, "generation": 1, "performance": 1, "improve": 1, "joint": 1, "distribution": 1, "match": 3, "problem": 1, "decompose": 1, "two": 1, "easier": 1, "subproblems": 1, "marginal": 1, "conditional": 1, "32": 1}, {"projection": 1, "cgan": 1, "decompose": 2, "density": 1, "ratio": 1, "acgan": 1, "tacgan": 1, "directly": 1, "distribution": 1}, {"projection": 1, "cgan": 1, "tacgan": 1, "theoretically": 1, "sound": 1, "use": 1, "crossentropy": 1, "loss": 1}, {"however": 1, "practice": 1, "hinge": 1, "loss": 1, "often": 1, "prefer": 1, "real": 1, "data": 1}, {"case": 1, "projection": 1, "cgan": 1, "lose": 1, "theoretical": 1, "guarantee": 1, "tacgan": 1, "less": 1, "affect": 1, "gin": 1, "loss": 2, "replace": 1, "hinge": 1}, {"4": 1, "": 2, "experiment": 1, "first": 1, "compare": 1, "distribution": 1, "match": 1, "ability": 1, "acgan": 1, "projection": 1, "cgan": 1, "tacgan": 1, "mixture": 1, "gaussian": 1, "mog": 1, "mnist": 1, "34": 1, "synthetic": 1, "data": 1}, {"evaluate": 1, "image": 2, "generation": 1, "performance": 1, "tacgan": 1, "three": 1, "datatest": 1, "include": 1, "cifar100": 1, "27": 1, "imagenet1000": 1, "25": 1, "vggface2": 1, "28": 1}, {"implementation": 1, "twin": 1, "auxiliary": 1, "classifiers": 1, "share": 1, "convolutional": 1, "layer": 1, "mean": 1, "tacgan": 1, "add": 1, "negligible": 1, "computation": 1, "cost": 1, "acgan": 1}, {"detail": 1, "experiment": 1, "setups": 1, "show": 1, "sm": 1}, {"implement": 1, "tacgan": 1, "pytorch": 1}, {"illustrate": 1, "algorithm": 1, "submit": 1, "implementation": 1, "synthetic": 1, "datasets": 1, "sm": 1}, {"source": 1, "code": 1, "reproduce": 1, "full": 1, "experimental": 1, "result": 1, "make": 1, "public": 1, "github": 1}, {"41": 1, "": 2, "mog": 1, "synthetic": 1, "data": 1, "start": 1, "simulate": 1, "dataset": 1, "verify": 1, "tacgan": 1, "accurately": 1, "match": 1, "target": 1, "distribution": 1}, {"draw": 1, "sample": 2, "onedimensional": 1, "mog": 2, "distribution": 2, "three": 1, "gaussian": 1, "components": 1, "label": 1, "5": 8, "": 66, "acgan": 2, "log": 3, "loss": 6, "tacgan": 2, "projection": 2, "cgan": 2, "05": 7, "04": 7, "03": 7, "02": 7, "01": 7, "00": 7, "10": 7, "0": 7, "density": 7, "target": 1, "15": 7, "hinge": 3, "figure": 1, "2": 1, "comparison": 1, "quality": 1, "synthetic": 1, "dataset": 1}, {"class0": 1, "projection": 1, "cgan": 1, "acgan": 1, "tacgan": 1, "": 50, "08": 1, "60": 2, "mmd": 5, "40": 2, "30": 2, "20": 2, "06": 1, "50": 2, "class1": 1, "04": 1, "class2": 1, "700": 1, "600": 1, "500": 1, "marginal": 1, "70": 1, "02": 1, "00": 1, "0": 3, "1": 4, "2": 4, "3": 5, "4": 4, "dmdistance": 1, "mean": 4, "5": 4, "100": 1, "dm": 3, "distance": 3, "300": 1, "200": 1, "10": 2, "400": 1, "figure": 1, "evaluation": 1}, {"xaxis": 1, "mean": 2, "distance": 1, "adjacent": 1, "gaussian": 1, "components": 1, "dm": 1, "": 1}, {"lower": 1, "score": 1, "better": 1}, {"class0": 1, "class1": 1, "class2": 1, "respectively": 1}, {"standard": 1, "deviations": 1, "three": 1, "components": 1, "fix": 1, "0": 1, "": 3, "1": 2, "2": 2, "3": 1}, {"differences": 1, "mean": 1, "set": 1, "1": 3, "": 5, "0": 1, "2": 1, "dm": 2, "range": 1, "5": 1}, {"value": 1, "choose": 1, "support": 1, "three": 1, "distributions": 1, "different": 1, "overlap": 1, "size": 1}, {"detail": 1, "experimental": 1, "setup": 1, "section": 1, "s4": 1, "sm": 1}, {"figure": 1, "2": 2, "show": 1, "grind": 1, "truth": 1, "density": 1, "function": 1, "0": 2, "": 3, "1": 1, "3": 1, "6": 1, "estimate": 1, "ones": 1, "acgan": 1, "tacgan": 1, "projection": 1, "cgan": 1}, {"estimate": 1, "density": 2, "function": 1, "obtain": 1, "apply": 1, "kernel": 1, "estimation": 1, "35": 1, "generate": 1, "data": 1}, {"use": 1, "crossentropy": 1, "loss": 1, "acgan": 1, "learn": 1, "bias": 1, "distribution": 1, "class": 1, "perfectly": 1, "separate": 1, "classification": 1, "decision": 1, "function": 1, "verify": 1, "theorem": 1, "1": 1}, {"tacgan": 1, "projection": 1, "cgan": 1, "accurately": 1, "learn": 1, "original": 1, "distribution": 1}, {"use": 1, "hinge": 1, "loss": 1, "model": 1, "still": 1, "learn": 1, "distribution": 2, "well": 1, "neither": 1, "acgan": 1, "projection": 1, "cgan": 1, "replicate": 1, "real": 1, "see": 1, "supplementary": 1, "s4": 1, "experiment": 1}, {"also": 1, "conduct": 1, "simulation": 1, "2d": 1, "dataset": 1, "detail": 1, "give": 1, "supplementary": 1, "s5": 1}, {"result": 1, "show": 1, "tacgan": 1, "able": 1, "learn": 1, "true": 1, "data": 1, "distribution": 1}, {"figure": 1, "3": 1, "report": 1, "maximum": 1, "mean": 1, "discrepancy": 1, "mmd": 1, "36": 1, "distance": 1, "real": 1, "data": 2, "generate": 1, "different": 1, "dm": 1, "value": 1}, {"gin": 1, "model": 1, "train": 1, "use": 1, "crossentropy": 1, "loss": 2, "log": 1}, {"tacgan": 2, "produce": 1, "nearzero": 1, "mmd": 1, "value": 1, "dm": 1, "mean": 1, "data": 2, "generate": 1, "close": 1, "grind": 1, "truth": 1}, {"projection": 1, "cgan": 1, "perform": 1, "slightly": 1, "worse": 1, "tacgan": 1, "acgan": 1, "generate": 1, "data": 2, "large": 1, "mmd": 1, "distance": 1, "true": 1}, {"42": 1, "": 2, "overlap": 2, "mnist": 2, "follow": 1, "experiment": 1, "33": 1, "show": 1, "acgan": 1, "learn": 1, "bias": 1, "distribution": 1, "use": 1, "dataset": 1, "demonstrate": 1, "robustness": 1, "tacgan": 1}, {"randomly": 1, "sample": 1, "mnist": 1, "train": 1, "set": 1, "construct": 1, "two": 1, "image": 1, "group": 4, "contain": 2, "5000": 4, "digit": 5, "1": 1, "0": 2, "b": 1, "2": 1, "0to": 1, "simulate": 1, "overlap": 1, "distributions": 1, "appear": 1}, {"note": 1, "grind": 1, "truth": 1, "proportion": 1, "digit": 1, "0": 1, "1": 1, "2": 1, "dataset": 1, "05": 1, "025": 2, "respectively": 1}, {"figure": 1, "4": 1, "show": 1, "generate": 1, "image": 1, "different": 1, "c": 1, "": 1}, {"show": 1, "acgan": 1, "tend": 1, "sample": 1, "0": 1, "c": 1, "increase": 1, "tacgan": 1, "always": 1, "generate": 1, "0s": 1, "group": 1}, {"quantitatively": 1, "measure": 1, "distribution": 1, "generate": 2, "image": 1, "pretrain": 1, "perfect": 1, "classifier": 2, "mnist": 1, "subset": 1, "contain": 1, "digit": 1, "0": 1, "1": 1, "2": 1, "use": 1, "predict": 1, "label": 1, "data": 1}, {"figure": 1, "4": 1, "b": 1, "report": 1, "label": 1, "proportion": 1, "generate": 1, "image": 1}, {"show": 1, "label": 1, "proportion": 1, "produce": 1, "tacgan": 1, "close": 1, "grind": 1, "truth": 1, "value": 1, "regardless": 1, "c": 2, "": 1, "acgan": 1, "generate": 1, "less": 1, "0s": 1, "increase": 1}, {"result": 1, "detail": 1, "set": 1, "show": 1, "section": 1, "s6": 1, "sm": 1}, {"6": 1, "": 8, "acgan": 4, "0": 2, "tacgan": 3, "real": 1, "data": 1, "1": 2, "2": 2, "05": 1, "relative": 1, "frequency": 1}, {"": 2, "1": 1, "tacgan": 1}, {"": 2, "1": 1, "acgan": 1}, {"": 2, "2": 1, "tacgan": 1}, {"": 15, "2": 1, "04": 1, "03": 1, "02": 1, "01": 1, "05": 1, "10": 1, "15": 1, "20": 1, "25": 1, "30": 1, "weight": 1, "classifier": 1, "c": 2, "b": 2, "generate": 2, "sample": 1, "quantitative": 1, "result": 1, "latexit": 2, "sha1base64ujrvwuxzgahtwgv18ozcvqibs4eaaab6nicbvbns8naej34wetx1aoxxslus0lu0gpri8ek9gpaudbbtbt0swm7e6gegqvhhtx6iy5r9x2agrq8ghunmdmvskqw6lrfzsrq2vrgzmgrul2zu7dfojhsmjjvjddylgpddqjhuijeqigstxpnarri3gpgt1o9cs1ebf6xhhcygolagfo2ilhwo965xkbtwdgswtlydlyfhvlb66zilevfijdwm47kjhnvkjjkk2i3ntyhbeqhvgopohe3fjy7dujordinyaxtksqz9fderinjxlfgoyokq7potcxve6k4bwfczwkybwblwptstam079jx2joui4touwleythq6opq5to0ybglb68tjrnvei6t1flms3erwfoiytqiahv1cdo6hdaxgm4ble4c2rzovz7nzmw1ecfoyisd5agjp41nlatexit": 1, "sha1base64go5upaekznw8gmcntj1tvcnpo8aaab6nicbvbns8naej34wetx1aoxxslus0lu0gpri8ek9gpaudbbsbt0swm7g6gegqvhhtx6iy5r9x2agrq8ghunmdmvsatxxnwnzxvtfwnzcjwcxtnd2dhdy1hgqgdzylglvdqhgwsu2ddcc24lcggucw8hoduq3nlbphsthm07qjha8pazaqz0uanoeqwyw3vnimvey0kzctr7pa9up2zphniwqbxueg5iiwqw5nasbgbakwog9ebdiyvneltz7ntjtukn0sxsqwngsmp7iakt1oapsz0tnuc96uer5oa8nrpuexsg5lnf4wpicym079jnytkrowtouxxeythq6oomzadog3bw3x5mttpq95f1bulndu8jgkcawnuaeprqagd1chbjaywdo8wpsjnbfn3fmyt644cwrihzqolli1olatexit": 1, "figure": 1, "4": 1, "visualization": 1, "mnist": 1, "digits": 1, "various": 1, "value": 1}, {"section": 1, "top": 1, "row": 2, "digits": 2, "sample": 1, "group": 2, "bottom": 1, "b": 1}, {"b": 1, "label": 1, "proportion": 1, "generate": 1, "digits": 1, "two": 1, "methods": 1}, {"grind": 1, "truth": 1, "proportion": 1, "digit": 1, "012": 1, "05": 1, "025": 2, "visualize": 1, "dash": 1, "dark": 1, "line": 1}, {"acgan": 1, "": 9, "02": 1, "tacgan": 1, "10": 1, "projection": 1, "cgan": 1, "apple": 1, "fish": 1, "tree": 1, "motorcycle": 1, "mountain": 1, "figure": 1, "5": 1, "generate": 1, "image": 1, "five": 1, "class": 1, "cifar100": 1}, {"80": 1, "": 29, "8": 1, "6": 2, "03": 1, "60": 1, "lpips": 1, "tacgan": 1, "acgan": 1, "fid": 1, "inception": 1, "score": 1, "10": 4, "40": 1, "20": 1, "02": 4, "04": 3, "06": 3, "08": 3, "weight": 3, "classifier": 3, "01": 1, "00": 1, "figure": 1, "impact": 1, "c": 1, "image": 1, "generation": 1, "quality": 1, "cifar100": 1}, {"43": 1, "": 3, "cifar100": 2, "27": 1, "100": 2, "class": 1, "contain": 1, "500": 1, "train": 1, "image": 2, "test": 1, "resolution": 1, "32": 2}, {"current": 1, "best": 1, "deep": 1, "classification": 1, "model": 1, "achieve": 1, "913": 1, "accuracy": 1, "dataset": 1, "37": 1, "suggest": 1, "class": 1, "distributions": 1, "may": 1, "certain": 1, "support": 1, "overlap": 1}, {"figure": 1, "5": 1, "show": 1, "generate": 1, "image": 1, "five": 1, "randomly": 1, "select": 1, "class": 1}, {"acgan": 1, "generate": 1, "image": 1, "low": 1, "intraclass": 1, "diversity": 1}, {"tacgan": 1, "projection": 1, "cgan": 1, "generate": 1, "visually": 1, "appeal": 1, "diverse": 1, "image": 1}, {"provide": 1, "generate": 1, "image": 1, "class": 1, "section": 1, "s6": 1, "sm": 1}, {"quantitatively": 1, "compare": 1, "generate": 1, "image": 1, "consider": 1, "two": 1, "popular": 1, "evaluation": 1, "criteria": 1, "include": 1, "inception": 2, "score": 1, "38": 1, "frchet": 1, "distance": 1, "fid": 1, "39": 1}, {"also": 1, "use": 1, "recently": 1, "propose": 1, "learn": 1, "perceptual": 2, "image": 1, "patch": 1, "similarity": 1, "lpips": 1, "measure": 1, "diversity": 1, "within": 1, "class": 1, "40": 1}, {"score": 1, "report": 1, "table": 1, "1": 1}, {"tacgan": 1, "achieve": 1, "lower": 1, "fid": 1, "projection": 1, "cgan": 1, "outperform": 1, "acgan": 1, "large": 1, "margin": 1, "demonstrate": 1, "efficacy": 1, "twin": 1, "auxiliary": 1, "classifiers": 1}, {"report": 1, "score": 1, "class": 1, "section": 1, "s7": 1, "sm": 1}, {"section": 1, "s72": 1, "sm": 1, "explore": 1, "compatibility": 1, "model": 1, "techniques": 1, "increase": 1, "diversity": 1, "unsupervised": 1, "gans": 1}, {"specifically": 1, "combine": 1, "pacgan": 2, "41": 1, "acgan": 3, "tacgan": 2, "result": 1, "show": 1, "improve": 1, "cannot": 1, "fully": 1, "address": 1, "drawbacks": 1}, {"effect": 1, "hyperparameters": 1, "c": 1, "": 1}, {"study": 1, "impact": 1, "c": 2, "acgan": 1, "tacgan": 1, "report": 1, "result": 1, "different": 1, "value": 1, "figure": 1, "6": 1}, {"show": 1, "tacgan": 1, "robust": 1, "c": 2, "": 1, "acgan": 1, "require": 1, "small": 1, "achieve": 1, "good": 1, "score": 1}, {"even": 1, "acgan": 1, "generate": 1, "image": 1, "low": 1, "intraclass": 1, "diversity": 1, "show": 1, "figure": 1, "5": 1}, {"7": 2, "": 7, "tacgan": 1, "acgan": 1, "projection": 1, "cgan": 1, "id": 3, "1": 1, "2": 1, "3": 1, "figure": 1, "comparison": 1, "generate": 1, "face": 1, "sample": 1, "three": 1, "identities": 1, "vggface2": 1, "dataset": 1}, {"table": 1, "1": 1, "quantitative": 1, "result": 1, "model": 1, "three": 1, "datasets": 1}, {"methods": 1, "": 75, "44": 1, "acgan": 1, "c": 2, "1": 2, "tacgan": 2, "projection": 1, "cgan": 1, "metrics": 1, "fid": 3, "cifar100": 1, "537": 1, "0064": 1, "8245": 1, "934": 1, "0077": 1, "722": 1, "956": 1, "0133": 1, "892": 1, "imagenet1000": 2, "726": 1, "0113": 1, "18441": 1, "2886": 1, "0298": 1, "2375": 1, "3805": 1, "0790": 1, "2277": 1, "vggface200": 1, "2781": 1, "029": 1, "9570": 1, "4894": 1, "063": 1, "2912": 1, "3250": 1, "044": 1, "6623": 1, "vggface500": 1, "2596": 1, "032": 1, "3190": 1, "7776": 1, "161": 1, "1242": 1, "3596": 1, "062": 1, "4310": 1, "vggface1000": 1, "10889": 1, "263": 1, "1360": 1, "7115": 1, "093": 1, "2407": 1, "vggface2000": 1, "10904": 1, "244": 1, "1379": 1, "7951": 1, "103": 1, "2242": 1, "apply": 1, "largescale": 1, "imagenet": 1, "dataset": 1, "25": 1, "contain": 1, "1000": 1, "class": 1, "around": 1, "1300": 1, "image": 1}, {"preprocess": 1, "data": 1, "centercropping": 1, "resize": 1, "image": 1, "128": 2, "": 1}, {"detail": 1, "experimental": 1, "setup": 1, "attach": 1, "generate": 1, "image": 1, "section": 1, "s8": 1, "sm": 1}, {"table": 1, "1": 1, "report": 1, "fid": 1, "metrics": 1, "model": 1}, {"tacgan": 1, "outperform": 1, "acgan": 1, "large": 1, "margin": 1}, {"addition": 1, "tacgan": 1, "lower": 1, "projection": 1, "cgan": 1}, {"hypothesize": 1, "tacgan": 1, "chance": 1, "generate": 1, "image": 1, "belong": 1, "give": 1, "class": 1, "overlap": 1, "regions": 1, "aim": 1, "model": 1, "true": 1, "conditional": 1, "distribution": 1}, {"45": 1, "": 2, "vggface2": 2, "28": 1, "largescale": 1, "face": 1, "recognition": 1, "dataset": 1, "around": 1, "362": 1, "image": 1, "person": 1}, {"main": 1, "difference": 1, "cifar100": 1, "imagenet1000": 1, "dataset": 1, "finegrained": 1, "smaller": 1, "intraclass": 1, "diversities": 1, "make": 1, "generative": 1, "task": 1, "difficult": 1}, {"resize": 1, "centercropped": 1, "image": 1, "64": 2, "": 1}, {"compare": 1, "different": 1, "algorithms": 1, "randomly": 1, "choose": 1, "200": 1, "500": 1, "1000": 1, "2000": 1, "identities": 1, "construct": 1, "vggface200": 1, "vggface500": 1, "vggface1000": 1, "vggface2000": 1, "datasets": 1, "respectively": 1}, {"figure": 1, "7": 1, "show": 1, "generate": 1, "face": 1, "image": 1, "five": 1, "randomly": 1, "select": 1, "identities": 1, "vggface200": 1}, {"acgan": 1, "collapse": 1, "class": 2, "center": 1, "generate": 1, "similar": 1, "image": 1}, {"though": 1, "projection": 1, "cgan": 1, "generate": 1, "diverse": 1, "image": 1, "blurry": 1, "effect": 1}, {"tacgan": 1, "generate": 1, "diverse": 1, "sharp": 1, "image": 1}, {"quantitatively": 1, "compare": 1, "methods": 1, "finetune": 1, "inception": 1, "net": 1, "42": 1, "classifier": 1, "face": 1, "data": 1, "use": 1, "calculate": 1, "fid": 1, "score": 1}, {"report": 1, "fid": 1, "score": 1, "methods": 1, "table": 1, "1": 1}, {"show": 1, "tacgan": 1, "produce": 1, "much": 1, "betterhigher": 1, "betterlower": 1, "fid": 1, "score": 1, "projection": 1, "cgan": 1, "consistent": 1, "qualitative": 1, "observations": 1}, {"result": 1, "suggest": 1, "tacgan": 1, "promise": 1, "method": 1, "finegrained": 1, "datasets": 1}, {"generate": 1, "identities": 1, "attach": 1, "section": 1, "s9": 1, "sm": 1}, {"5": 1, "": 2, "conclusion": 1, "paper": 1, "theoretically": 1, "analyze": 1, "low": 1, "intraclass": 1, "diversity": 1, "problem": 1, "widely": 1, "use": 1, "acgan": 1, "method": 1, "distribution": 1, "match": 1, "perspective": 1}, {"show": 1, "auxiliary": 1, "classifier": 1, "acgan": 1, "impose": 1, "perfect": 1, "separability": 1, "disadvantageous": 1, "support": 1, "class": 1, "distributions": 1, "significant": 1, "overlap": 1}, {"base": 1, "analysis": 1, "propose": 1, "twin": 1, "auxiliary": 2, "classifiers": 1, "gin": 1, "tacgan": 1, "method": 1, "introduce": 1, "additional": 1, "classifier": 1, "adversarially": 1, "play": 1, "players": 1, "acgan": 1}, {"demonstrate": 1, "efficacy": 1, "propose": 1, "8": 1, "": 1, "method": 1, "theoretically": 1, "empirically": 1}, {"tacgan": 1, "resolve": 1, "issue": 1, "acgan": 1, "learn": 1, "unbiased": 1, "distribution": 1, "generate": 1, "highquality": 1, "sample": 1, "finegrained": 1, "image": 1, "datasets": 1}, {"acknowledgments": 1, "work": 1, "partially": 1, "support": 1, "nih": 1, "award": 1, "number": 1, "1r01hl14181301": 1, "nsf": 1, "1839332": 1, "tripodx": 1, "sap": 1, "se": 1}, {"gratefully": 1, "acknowledge": 1, "support": 1, "nvidia": 1, "corporation": 1, "donation": 1, "titan": 1, "x": 1, "pascal": 1, "gpu": 1, "use": 1, "research": 1}, {"also": 1, "grateful": 1, "computational": 1, "resources": 1, "provide": 1, "pittsburgh": 1, "supercomputing": 1, "grant": 1, "number": 1, "tgasc170024": 1}, {"reference": 1, "1": 1, "goodfellow": 1, "j": 1, "pougetabadie": 1, "mirza": 1, "b": 1, "xu": 1, "wardefarley": 1, "ozair": 1, "courville": 1, "bengio": 1}, {"generative": 1, "adversarial": 1, "net": 1}, {"nip": 1, "2014": 1}, {"2": 1, "sebastian": 1, "nowozin": 1, "botond": 1, "cseke": 1, "ryota": 1, "tomioka": 1}, {"fgan": 1, "train": 1, "generative": 1, "neural": 1, "samplers": 1, "use": 1, "variational": 1, "divergence": 1, "minimization": 1}, {"nip": 1, "page": 1, "271279": 1, "2016": 1}, {"3": 1, "chunliang": 1, "li": 1, "weicheng": 1, "chang": 1, "yu": 1, "cheng": 1, "yiming": 1, "yang": 1, "barnabs": 1, "pczos": 1}, {"mmd": 1, "gin": 1, "towards": 1, "deeper": 1, "understand": 1, "moment": 1, "match": 1, "network": 1}, {"nip": 1, "page": 1, "22032213": 1, "2017": 1}, {"4": 1, "mikolaj": 1, "binkowski": 1, "dougal": 1, "j": 1, "sutherland": 1, "michael": 1, "arbel": 1, "arthur": 1, "gretton": 1}, {"demystify": 1, "mmd": 1, "gans": 1}, {"corr": 1, "abs180101401": 1, "2018": 1}, {"5": 1, "alec": 1, "radford": 1, "luke": 1, "metz": 1, "soumith": 1, "chintala": 1}, {"unsupervised": 1, "representation": 1, "learn": 1, "deep": 1, "convolutional": 1, "generative": 1, "adversarial": 1, "network": 1}, {"iclr": 1, "2016": 1}, {"6": 1, "han": 1, "zhang": 1, "ian": 1, "j": 1, "goodfellow": 1, "dimitris": 1, "n": 1, "metaxas": 1, "augustus": 1, "odena": 1}, {"selfattention": 1, "generative": 1, "adversarial": 1, "network": 1}, {"arxiv180508318": 1, "2018": 1}, {"7": 1, "tim": 1, "salimans": 1, "ian": 1, "goodfellow": 1, "wojciech": 1, "zaremba": 1, "vicki": 1, "cheung": 1, "alec": 1, "radford": 1, "xi": 1, "chen": 1}, {"improve": 1, "techniques": 1, "train": 1, "gin": 1}, {"nip": 1, "page": 1, "22342242": 1, "2016": 1}, {"8": 1, "martin": 1, "arjovsky": 1, "soumith": 1, "chintala": 1, "lon": 1, "bottou": 1}, {"wasserstein": 1, "generative": 1, "adversarial": 1, "network": 1}, {"icml": 1, "page": 1, "214223": 1, "2017": 1}, {"9": 1, "xudong": 1, "mao": 1, "qing": 1, "li": 1, "haoran": 1, "xie": 1, "raymond": 1, "yk": 1, "lau": 1, "zhen": 1, "wang": 1, "stephen": 1, "paul": 1, "smolley": 1}, {"least": 1, "square": 1, "generative": 1, "adversarial": 1, "network": 1}, {"iccv": 1, "page": 1, "27942802": 1, "2017": 1}, {"10": 1, "ishaan": 1, "gulrajani": 1, "faruk": 1, "ahmed": 1, "martin": 1, "arjovsky": 1, "vincent": 1, "dumoulin": 1, "aaron": 1, "c": 1, "courville": 1}, {"improve": 1, "train": 1, "wasserstein": 1, "gin": 1}, {"nip": 1, "page": 1, "57675777": 1, "2017": 1}, {"11": 1, "lars": 1, "mescheder": 1, "sebastian": 1, "nowozin": 1, "andreas": 1, "geiger": 1}, {"train": 1, "methods": 1, "gans": 1, "actually": 1, "converge": 1}, {"icml": 1, "2018": 1}, {"12": 1, "takeru": 1, "miyato": 1, "toshiki": 1, "kataoka": 1, "masanori": 1, "koyama": 1, "yuichi": 1, "yoshida": 1}, {"spectral": 1, "normalization": 1, "generative": 1, "adversarial": 1, "network": 1}, {"iclr": 1, "2018": 1}, {"13": 1, "andrew": 1, "brock": 1, "jeff": 1, "donahue": 1, "karen": 1, "simonyan": 1}, {"large": 1, "scale": 1, "gin": 1, "train": 1, "high": 1, "fidelity": 1, "natural": 1, "image": 1, "synthesis": 1}, {"iclr": 1, "2019": 1}, {"14": 1, "mirza": 1, "osindero": 1}, {"conditional": 1, "generative": 1, "adversarial": 1, "net": 1}, {"arxiv": 1, "preprint": 1, "arxiv14111784": 1, "2014": 1}, {"15": 1, "phillip": 1, "isola": 1, "junyan": 1, "zhu": 1, "tinghui": 1, "zhou": 1, "alexei": 1, "efros": 1}, {"imagetoimage": 1, "translation": 1, "conditional": 1, "adversarial": 1, "network": 1}, {"arxiv": 1, "2016": 1}, {"16": 1, "anh": 1, "nguyen": 1, "jeff": 1, "clune": 1, "yoshua": 1, "bengio": 1, "alexey": 1, "dosovitskiy": 1, "jason": 1, "yosinski": 1}, {"plug": 1, "": 1, "play": 1, "generative": 1, "network": 1, "conditional": 1, "iterative": 1, "generation": 1, "image": 1, "latent": 1, "space": 1}, {"cvpr": 1, "page": 1, "44674477": 1, "2017": 1}, {"17": 1, "augustus": 1, "odena": 1, "christopher": 1, "olah": 1, "jonathon": 1, "shlens": 1}, {"conditional": 1, "image": 1, "synthesis": 1, "auxiliary": 1, "classifier": 1, "gans": 1}, {"icml": 1, "page": 1, "26422651": 1}, {"jmlr": 1}, {"org": 1, "2017": 1}, {"18": 1, "dingdong": 1, "yang": 1, "seunghoon": 1, "hong": 1, "yunseok": 1, "jang": 1, "tianchen": 1, "zhao": 1, "honglak": 1, "lee": 1}, {"diversitysensitive": 1, "conditional": 1, "generative": 1, "adversarial": 1, "network": 1}, {"iclr": 1, "2019": 1}, {"19": 1, "scott": 1, "reed": 1, "zeynep": 1, "akata": 1, "xinchen": 1, "yan": 1, "lajanugen": 1, "logeswaran": 1, "bernt": 1, "schiele": 1, "honglak": 1, "lee": 1}, {"generative": 1, "adversarial": 1, "text": 1, "image": 1, "synthesis": 1}, {"maria": 1, "florina": 1, "balcan": 1, "kilian": 1, "q": 1, "weinberger": 1, "editors": 1, "icml": 1, "page": 1, "10601069": 1, "2016": 1}, {"9": 1, "": 1, "20": 1, "han": 1, "zhang": 2, "tao": 1, "xu": 1, "hongsheng": 1, "li": 1, "shaoting": 1, "xiaogang": 1, "wang": 1, "xiaolei": 1, "huang": 1, "dimitris": 1, "n": 1, "metaxas": 1}, {"stackgan": 1, "text": 1, "photorealistic": 1, "image": 1, "synthesis": 1, "stack": 1, "generative": 1, "adversarial": 1, "network": 1}, {"iccv": 1, "page": 1, "59075915": 1, "2017": 1}, {"21": 1, "emily": 1, "l": 1, "denton": 1, "soumith": 1, "chintala": 1, "rob": 1, "fergus": 1, "et": 1, "al": 1}, {"deep": 1, "generative": 1, "image": 1, "model": 1, "use": 1, "laplacian": 1, "pyramid": 1, "adversarial": 1, "network": 1}, {"nip": 1, "page": 1, "14861494": 1, "2015": 1}, {"22": 1, "guim": 1, "perarnau": 1, "joost": 1, "van": 1, "de": 1, "weijer": 1, "bogdan": 1, "raducanu": 1, "jose": 1, "lvarez": 1}, {"invertible": 1, "conditional": 1, "gans": 1, "image": 1, "edit": 1}, {"arxiv": 1, "preprint": 1, "arxiv161106355": 1, "2016": 1}, {"23": 1, "vincent": 1, "dumoulin": 1, "ishmael": 1, "belghazi": 1, "ben": 1, "poole": 1, "olivier": 1, "mastropietro": 1, "alex": 1, "lamb": 1, "martin": 1, "arjovsky": 1, "aaron": 1, "courville": 1}, {"adversarially": 1, "learn": 1, "inference": 1}, {"arxiv": 1, "preprint": 1, "arxiv160600704": 1, "2016": 1}, {"24": 1, "takeru": 1, "miyato": 1, "masanori": 1, "koyama": 1}, {"cgans": 1, "projection": 1, "discriminator": 1}, {"iclr": 1, "2018": 1}, {"25": 1, "olga": 1, "russakovsky": 1, "jia": 1, "deng": 1, "hao": 1, "su": 1, "jonathan": 1, "krause": 1, "sanjeev": 1, "satheesh": 1, "sean": 1, "zhiheng": 1, "huang": 1, "andrej": 1, "karpathy": 1, "aditya": 1, "khosla": 1, "michael": 1, "bernstein": 1, "alexander": 1, "c": 1, "berg": 1, "li": 1, "feifei": 1}, {"imagenet": 1, "large": 1, "scale": 1, "visual": 1, "recognition": 1, "challenge": 1}, {"ijcv": 1, "1153211252": 1, "2015": 1}, {"26": 1, "ayushman": 1, "dash": 1, "john": 1, "cristian": 1, "borges": 1, "gamboa": 1, "sheraz": 1, "ahmed": 1, "marcus": 1, "liwicki": 1, "muhammad": 1, "zeshan": 1, "afzal": 1}, {"tacgantext": 1, "condition": 1, "auxiliary": 1, "classifier": 1, "generative": 1, "adversarial": 1, "network": 1}, {"arxiv": 1, "preprint": 1, "arxiv170306412": 1, "2017": 1}, {"27": 1, "alex": 1, "krizhevsky": 1, "vinod": 1, "nair": 1, "geoffrey": 1, "hinton": 1}, {"cifar100": 1, "canadian": 1, "institute": 1, "advance": 1, "research": 1}, {"28": 1, "qiong": 1, "cao": 1, "li": 1, "shen": 1, "weidi": 1, "xie": 1, "omkar": 1, "parkhi": 1, "andrew": 1, "zisserman": 1}, {"vggface2": 1, "dataset": 1, "recognise": 1, "face": 1, "across": 1, "pose": 1, "age": 1}, {"fg": 1}, {"ieee": 1, "computer": 1, "society": 1, "2018": 1}, {"29": 1, "kumar": 1, "sricharan": 1, "dennis": 1, "wei": 1, "alfred": 1, "hero": 1}, {"ensemble": 1, "estimators": 1, "multivariate": 1, "entropy": 1, "estimation": 1}, {"ieee": 1, "transactions": 1, "information": 1, "theory": 1, "59743744388": 1, "2013": 1}, {"30": 1, "shashank": 1, "singh": 1, "barnabs": 1, "pczos": 1}, {"finitesample": 1, "analysis": 1, "fixedk": 1, "nearest": 1, "neighbor": 1, "density": 1, "functional": 1, "estimators": 1}, {"nip": 1, "page": 1, "12171225": 1, "2016": 1}, {"31": 1, "weihao": 1, "gao": 1, "sreeram": 1, "kannan": 1, "sewoong": 1, "oh": 1, "pramod": 1, "viswanath": 1}, {"estimate": 1, "mutual": 1, "information": 1, "discretecontinuous": 1, "mixtures": 1}, {"nip": 1, "page": 1, "59865997": 1, "2017": 1}, {"32": 1, "chunyuan": 1, "li": 1, "hao": 1, "liu": 1, "changyou": 1, "chen": 2, "yuchen": 1, "pu": 1, "liqun": 1, "ricardo": 1, "henao": 1, "lawrence": 1, "carin": 1}, {"alice": 1, "towards": 1, "understand": 1, "adversarial": 1, "learn": 1, "joint": 1, "distribution": 1, "match": 1}, {"nip": 1, "2017": 1}, {"33": 1, "rui": 1, "shu": 1, "hang": 1, "bui": 1, "stefano": 1, "ermon": 1}, {"acgan": 1, "learn": 1, "bias": 1, "distribution": 1}, {"34": 1, "yann": 1, "lecun": 1}, {"mnist": 1, "database": 1, "handwritten": 1, "digits": 1}, {"httpyann": 1}, {"lecun": 1}, {"comexdbmnist": 1}, {"35": 1, "emanuel": 1, "parzen": 1}, {"estimation": 1, "probability": 1, "density": 1, "function": 1, "mode": 1}, {"annals": 1, "mathematical": 1, "statistics": 1, "1962": 1}, {"36": 1, "arthur": 1, "gretton": 1, "karsten": 1, "borgwardt": 1, "malte": 1, "j": 1, "rasch": 1, "bernhard": 1, "schlkopf": 1, "alexander": 1, "smola": 1}, {"kernel": 1, "twosample": 1, "test": 1}, {"j": 1, "mach": 1}, {"learn": 1}, {"res": 1, "2012": 1}, {"37": 1, "yanping": 1, "huang": 1, "yonglong": 1, "cheng": 1, "dehao": 1, "chen": 2, "hyoukjoong": 1, "lee": 1, "jiquan": 1, "ngiam": 1, "quoc": 1, "v": 1, "le": 1, "zhifeng": 1}, {"gpipe": 1, "efficient": 1, "train": 1, "giant": 1, "neural": 1, "network": 1, "use": 1, "pipeline": 1, "parallelism": 1}, {"arxiv": 1, "preprint": 1, "arxiv181106965": 1, "2018": 1}, {"38": 1, "tim": 1, "salimans": 1, "ian": 1, "j": 1, "goodfellow": 1, "wojciech": 1, "zaremba": 1, "vicki": 1, "cheung": 1, "alec": 1, "radford": 1, "xi": 1, "chen": 1}, {"improve": 1, "techniques": 1, "train": 1, "gans": 1}, {"corr": 1, "abs160603498": 1, "2016": 1}, {"39": 1, "martin": 1, "heusel": 1, "hubert": 1, "ramsauer": 1, "thomas": 1, "unterthiner": 1, "bernhard": 1, "nessler": 1, "gnter": 1, "klambauer": 1, "sepp": 1, "hochreiter": 1}, {"gans": 1, "train": 1, "two": 1, "timescale": 1, "update": 1, "rule": 1, "converge": 1, "nash": 1, "equilibrium": 1}, {"corr": 1, "abs170608500": 1, "2017": 1}, {"40": 1, "richard": 1, "zhang": 1, "phillip": 1, "isola": 1, "alexei": 1, "efros": 1, "eli": 1, "shechtman": 1, "oliver": 1, "wang": 1}, {"unreasonable": 1, "effectiveness": 1, "deep": 1, "feature": 1, "perceptual": 1, "metric": 1}, {"cvpr": 1, "page": 1, "586595": 1, "2018": 1}, {"41": 1, "zinan": 1, "lin": 1, "ashish": 1, "khetan": 1, "giulia": 1, "fanti": 1, "sewoong": 1, "oh": 1}, {"pacgan": 1, "power": 1, "two": 1, "sample": 1, "generative": 1, "adversarial": 1, "network": 1}, {"neurips": 1, "page": 1, "14981507": 1, "2018": 1}, {"42": 1, "christian": 1, "szegedy": 1, "vincent": 1, "vanhoucke": 1, "sergey": 1, "ioffe": 1, "jonathon": 1, "shlens": 1, "zbigniew": 1, "wojna": 1}, {"rethink": 1, "inception": 1, "architecture": 1, "computer": 1, "vision": 1}, {"corr": 1, "abs151200567": 1, "2015": 1}, {"10": 1}]