[{"cold": 1, "case": 1, "lose": 2, "mnist": 2, "digits": 1, "chhavi": 1, "yadav": 1, "new": 4, "york": 4, "university": 2, "ny": 2, "chhavinyuedu": 1, "": 2, "lon": 1, "bottou": 1, "facebook": 1, "ai": 1, "research": 1, "leonbottouorg": 1, "abstract": 1, "although": 1, "popular": 1, "dataset": 1, "lecun": 1, "et": 1, "al": 1, "1994": 1, "derive": 1, "nist": 1, "database": 1, "grother": 1, "hanaoka": 1, "1995": 1, "precise": 1, "process": 1, "step": 1, "derivation": 1, "time": 1}, {"propose": 1, "reconstruction": 1, "accurate": 1, "enough": 1, "serve": 1, "replacement": 1, "mnist": 1, "dataset": 1, "insignificant": 1, "change": 1, "accuracy": 1}, {"trace": 1, "mnist": 1, "digit": 1, "nist": 1, "source": 1, "rich": 1, "metadata": 1, "writer": 1, "identifier": 2, "partition": 1, "etc": 1}, {"also": 1, "reconstruct": 1, "complete": 1, "mnist": 1, "test": 1, "set": 1, "60000": 1, "sample": 1, "instead": 1, "usual": 1, "10000": 1}, {"since": 1, "balance": 1, "50000": 1, "never": 1, "distribute": 1, "use": 1, "investigate": 1, "impact": 1, "twentyfive": 1, "years": 1, "mnist": 1, "experiment": 1, "report": 1, "test": 1, "performances": 1}, {"limit": 1, "result": 1, "unambiguously": 1, "confirm": 1, "trend": 1, "observe": 1, "recht": 1, "et": 1, "al": 1}, {"2018": 1, "2019": 1, "although": 1, "misclassification": 1, "rat": 1, "slightly": 1, "classifier": 1, "order": 1, "model": 1, "selection": 1, "remain": 1, "broadly": 1, "reliable": 1}, {"attribute": 1, "phenomenon": 1, "pair": 1, "benefit": 1, "compare": 1, "classifiers": 1, "digits": 1}, {"1": 1, "": 2, "introduction": 1, "mnist": 1, "dataset": 1, "lecun": 1, "et": 2, "al": 2, "1994": 2, "bottou": 1, "use": 1, "standard": 1, "machine": 1, "learn": 1, "benchmark": 1, "twenty": 1, "years": 1}, {"last": 1, "decade": 1, "many": 1, "researchers": 1, "express": 1, "opinion": 1, "dataset": 1, "overuse": 1}, {"particular": 1, "small": 1, "size": 1, "test": 1, "set": 1, "merely": 1, "10000": 1, "sample": 1, "cause": 1, "concern": 1}, {"hundreds": 1, "publications": 1, "report": 1, "increasingly": 1, "good": 1, "performance": 1, "test": 1, "set": 1}, {"overfit": 1, "test": 1, "set": 1}, {"trust": 1, "new": 1, "conclusion": 1, "draw": 1, "dataset": 1}, {"quickly": 1, "machine": 1, "learn": 1, "datasets": 1, "become": 1, "useless": 1}, {"first": 1, "partition": 1, "large": 1, "nist": 1, "handwritten": 1, "character": 1, "collection": 1, "grother": 1, "hanaoka": 1, "1995": 1, "release": 1, "one": 1, "year": 1, "earlier": 1, "train": 1, "set": 2, "write": 2, "2000": 1, "census": 1, "bureau": 1, "employees": 1, "substantially": 1, "challenge": 1, "test": 1, "500": 1, "high": 1, "school": 1, "students": 1}, {"one": 1, "objectives": 1, "lecun": 1, "cortes": 1, "burges": 1, "create": 1, "dataset": 1, "similarly": 1, "distribute": 1, "train": 1, "test": 1, "set": 1}, {"process": 1, "describe": 1, "produce": 1, "two": 1, "set": 1, "60000": 1, "sample": 1}, {"test": 1, "set": 1, "downsampled": 1, "10000": 1, "sample": 1, "possibly": 1, "manipulate": 1, "dataset": 1, "computers": 1, "time": 1, "could": 1, "annoyingly": 1, "slow": 1}, {"remain": 1, "50000": 1, "test": 1, "sample": 1, "since": 1, "lose": 1}, {"initial": 1, "purpose": 1, "work": 1, "recreate": 1, "mnist": 2, "preprocessing": 1, "algorithms": 1, "order": 1, "trace": 1, "back": 1, "digit": 1, "original": 1, "writer": 1, "nist": 1}, {"reconstruction": 1, "first": 1, "base": 1, "available": 1, "information": 1, "considerably": 1, "improve": 1, "iterative": 1, "refinements": 1}, {"section": 1, "2": 1, "describe": 1, "process": 1, "measure": 1, "closely": 1, "reconstruct": 1, "sample": 2, "match": 1, "official": 1, "mnist": 1}, {"reconstruct": 1, "train": 2, "set": 1, "contain": 1, "60000": 1, "image": 2, "match": 1, "mnist": 1}, {"similarly": 1, "first": 1, "10000": 1, "image": 2, "reconstruct": 1, "test": 2, "set": 2, "match": 1, "mnist": 1}, {"next": 1, "50000": 2, "image": 1, "reconstruction": 1, "lose": 1, "mnist": 1, "test": 1, "images1": 1, "1": 1, "": 1, "code": 1, "data": 1, "available": 1, "httpsgithubcomfacebookresearchqmnist": 1}, {"33rd": 1, "conference": 1, "neural": 1, "information": 1, "process": 1, "systems": 1, "neurips": 1, "2019": 1, "vancouver": 1, "canada": 1}, {"original": 1, "nist": 1, "test": 1, "contain": 1, "58527": 1, "digit": 1, "image": 1, "write": 1, "500": 1, "different": 1, "writers": 1}, {"contrast": 1, "train": 1, "set": 2, "block": 1, "data": 2, "writer": 1, "appear": 1, "sequence": 1, "nist": 1, "test": 1, "scramble": 1}, {"writer": 1, "identities": 1, "test": 1, "set": 1, "available": 1, "use": 1, "information": 1, "unscramble": 1, "writers": 1}, {"split": 1, "nist": 1, "test": 1, "set": 2, "two": 1, "character": 1, "write": 1, "first": 1, "250": 1, "writers": 1, "go": 1, "new": 1, "train": 1}, {"remain": 1, "250": 1, "writers": 1, "place": 1, "test": 1, "set": 1}, {"thus": 1, "two": 1, "set": 1, "nearly": 1, "30000": 1, "examples": 1}, {"new": 1, "train": 3, "set": 3, "complete": 1, "enough": 1, "sample": 1, "old": 1, "nist": 1, "start": 1, "pattern": 2, "0": 1, "make": 1, "full": 1, "60000": 1}, {"similarly": 1, "new": 1, "test": 2, "set": 2, "complete": 1, "old": 1, "train": 1, "examples": 1, "start": 1, "pattern": 2, "35000": 1, "make": 1, "full": 1, "60000": 1}, {"image": 2, "size": 1, "normalize": 1, "fit": 2, "20": 2, "x": 2, "pixel": 1, "box": 1, "center": 2, "28": 2, "use": 1, "gravity": 1}, {"grayscale": 1, "pixel": 1, "value": 1, "use": 1, "reduce": 1, "effect": 1, "aliasing": 1}, {"train": 1, "test": 1, "set": 1, "use": 1, "benchmarks": 1, "describe": 1, "paper": 1}, {"paper": 1, "call": 1, "mnist": 1, "data": 1}, {"figure": 1, "1": 1, "two": 1, "paragraph": 1, "bottou": 1, "et": 1, "al": 1}, {"1994": 1, "describe": 1, "mnist": 1, "preprocessing": 1}, {"hsf4": 1, "partition": 1, "nist": 1, "dataset": 1, "original": 1, "test": 1, "set": 1, "contain": 1, "fact": 1, "58646": 1, "digits": 1}, {"spirit": 1, "recht": 1, "et": 1, "al": 1, "2018": 1, "2019": 1, "rediscovery": 1, "50000": 1, "lose": 1, "mnist": 2, "test": 2, "digits": 1, "provide": 1, "opportunity": 1, "quantify": 1, "degradation": 1, "official": 1, "set": 1, "quartercentury": 1, "experimental": 1, "research": 1}, {"section": 1, "3": 1, "compare": 1, "discuss": 1, "performances": 1, "well": 1, "know": 1, "algorithms": 1, "measure": 1, "original": 1, "mnist": 1, "test": 2, "sample": 2, "reconstructions": 2, "50000": 1, "lose": 1}, {"result": 1, "provide": 1, "well": 1, "control": 1, "confirmation": 1, "trend": 1, "identify": 1, "recht": 1, "et": 1, "al": 1}, {"2018": 1, "2019": 1, "different": 1, "dataset": 1}, {"2": 1, "": 2, "recreate": 2, "mnist": 2, "algorithms": 1, "use": 1, "construct": 1, "dataset": 1, "challenge": 1, "task": 1}, {"figure": 1, "1": 1, "show": 1, "two": 1, "paragraph": 1, "describe": 1, "process": 1, "bottou": 1, "et": 1, "al": 1, "1994": 1}, {"although": 1, "first": 1, "paper": 1, "mention": 1, "mnist": 2, "creation": 1, "dataset": 1, "predate": 1, "benchmarking": 1, "effort": 1, "several": 1, "months2": 1, "curiously": 1, "description": 1, "incorrectly": 1, "report": 1, "number": 1, "digits": 2, "hsf4": 1, "partition": 1, "original": 1, "nist": 1, "test": 1, "set": 2, "58527": 1, "instead": 1, "586463": 1, "two": 1, "paragraph": 1, "give": 1, "relatively": 1, "precise": 1, "recipe": 1, "select": 1, "60000": 1, "compose": 1, "train": 1}, {"alas": 1, "apply": 1, "recipe": 1, "produce": 1, "set": 2, "contain": 1, "one": 2, "zero": 1, "less": 1, "eight": 1, "actual": 1, "mnist": 1, "train": 1}, {"although": 1, "match": 1, "class": 1, "distributions": 1, "close": 1, "make": 1, "plausible": 1, "119": 1, "digits": 1, "really": 1, "miss": 1, "hsf4": 1, "partition": 1}, {"description": 1, "image": 1, "process": 1, "step": 1, "much": 1, "less": 1, "precise": 1}, {"128x128": 1, "binary": 1, "nist": 1, "image": 1, "crop": 1}, {"heuristics": 1, "use": 1, "disregard": 1, "noisy": 1, "pixels": 1, "belong": 1, "digits": 1}, {"rectangular": 1, "crop": 1, "center": 1, "square": 1, "image": 1}, {"square": 1, "image": 2, "resampled": 1, "20x20": 1, "gray": 1, "level": 1}, {"coordinate": 1, "center": 2, "gravity": 1, "round": 1, "final": 1, "step": 1}, {"21": 1, "": 3, "iterative": 1, "process": 1, "initial": 1, "reconstruction": 1, "algorithms": 1, "inform": 1, "exist": 1, "description": 1, "crucially": 1, "knowledge": 1, "mysterious": 1, "resampling": 1, "algorithm": 1, "find": 1, "ancient": 1, "part": 1, "lush": 1, "codebase": 1, "instead": 1, "use": 1, "bilinear": 1, "bicubic": 1, "interpolation": 1, "code": 1, "compute": 1, "exact": 1, "overlap": 1, "input": 1, "output": 1, "image": 1, "pixels4": 1, "2": 1, "lb": 1, "join": 1, "effort": 1, "summer": 1, "1994": 1, "mnist": 1, "dataset": 1, "already": 1, "ready": 1}, {"description": 1, "also": 1, "appear": 1, "lecun": 1, "et": 2, "al": 2, "1994": 1, "le": 1, "cun": 1, "1998": 1}, {"recent": 1, "texts": 1, "incorrectly": 1, "use": 1, "name": 1, "sd1": 1, "sd3": 1, "denote": 1, "original": 1, "nist": 1, "test": 1, "train": 1, "set": 1}, {"additional": 1, "sentence": 1, "explain": 1, "subset": 1, "10000": 1, "test": 1, "image": 1, "use": 1, "make": 1, "available": 1, "5000": 2, "sd1": 1, "sd3": 1, "4": 1, "see": 1, "httpstinyurlcomy5z7qtcg": 1}, {"3": 1, "": 3, "2": 2, "magnification": 1, "mnist": 2, "0": 1, "nist": 1, "229421": 1, "figure": 1, "sidebyside": 1, "display": 1, "first": 1, "sixteen": 1, "digits": 1, "qmnist": 1, "train": 1, "set": 1}, {"magnify": 1, "view": 1, "first": 1, "one": 1, "illustrate": 1, "correct": 1, "reconstruction": 1, "antialiased": 1, "pixels": 1}, {"although": 1, "first": 1, "reconstruct": 1, "dataset": 1, "dub": 1, "qmnistv1": 1, "behave": 1, "much": 1, "like": 1, "mnist": 2, "machine": 1, "learn": 1, "experiment": 1, "digit": 1, "image": 1, "could": 1, "reliably": 1, "match": 1, "actual": 1, "digits": 1}, {"fact": 1, "many": 1, "digits": 1, "similar": 1, "shape": 1, "must": 1, "rely": 1, "subtler": 1, "detail": 1, "antialiasing": 1, "pixel": 1, "pattern": 1}, {"however": 1, "possible": 1, "identify": 1, "match": 1}, {"instance": 1, "find": 1, "lightest": 2, "zero": 2, "qmnist": 1, "train": 2, "set": 2, "match": 1, "mnist": 1}, {"able": 1, "reproduce": 1, "antialiasing": 1, "pattern": 1, "finetuning": 1, "initial": 1, "center": 1, "resampling": 1, "algorithms": 1, "lead": 1, "qmnistv2": 1}, {"find": 1, "smallest": 1, "l2": 1, "distance": 1, "mnist": 1, "digits": 2, "jittered": 1, "qmnist": 1, "reliable": 1, "match": 1, "indicator": 1}, {"run": 1, "hungarian": 1, "assignment": 1, "algorithm": 1, "two": 1, "train": 1, "set": 1, "give": 1, "good": 1, "match": 1, "digits": 1}, {"careful": 1, "inspection": 1, "worst": 1, "match": 1, "allow": 1, "us": 1, "tune": 1, "crop": 1, "algorithms": 1, "discover": 1, "instance": 1, "extra": 1, "zero": 1, "reconstruct": 1, "train": 1, "set": 1, "fact": 1, "duplicate": 1, "digit": 1, "mnist": 1, "creators": 1, "identify": 1, "remove": 1}, {"ability": 1, "obtain": 1, "reliable": 1, "match": 1, "allow": 1, "us": 1, "iterate": 1, "much": 1, "faster": 1, "explore": 1, "aspects": 1, "image": 1, "process": 1, "algorithm": 1, "space": 1, "lead": 1, "qmnistv3": 1, "v4": 1, "v5": 1}, {"note": 1, "tune": 1, "achieve": 1, "match": 1, "train": 1, "set": 1, "image": 1}, {"seemingly": 1, "pointless": 1, "quest": 1, "exact": 1, "reconstruction": 1, "surprisingly": 1, "addictive": 1}, {"supposedly": 1, "urgent": 1, "task": 1, "could": 1, "indefinitely": 1, "delay": 1, "important": 1, "procrastination": 1, "pretext": 1}, {"since": 1, "good": 1, "things": 1, "must": 1, "come": 1, "end": 1, "eventually": 1, "freeze": 1, "one": 1, "datasets": 1, "call": 1, "qmnist": 1}, {"22": 1, "": 2, "evaluate": 1, "reconstruction": 1, "quality": 1, "although": 1, "qmnist": 1, "reconstructions": 1, "closer": 1, "mnist": 1, "image": 1, "envision": 1, "remain": 1, "imperfect": 1}, {"table": 1, "2": 1, "indicate": 1, "025": 1, "qmnist": 1, "train": 1, "set": 1, "image": 1, "shift": 1, "one": 1, "pixel": 1, "relative": 1, "mnist": 1, "counterpart": 1}, {"occur": 1, "center": 2, "gravity": 1, "compute": 1, "last": 1, "step": 1, "see": 1, "figure": 1, "1": 1, "close": 1, "pixel": 1, "boundary": 1}, {"image": 2, "reconstruction": 1, "imperfect": 1, "reconstruct": 1, "center": 1, "gravity": 1, "sometimes": 1, "land": 1, "side": 1, "pixel": 2, "boundary": 1, "alignment": 1, "code": 1, "shift": 1, "whole": 1}, {"3": 1, "": 2, "table": 1, "1": 1, "quartiles": 1, "jittered": 1, "distance": 1, "match": 1, "mnist": 1, "qmnist": 1, "train": 1, "digit": 1, "image": 1, "pixels": 1, "range": 1, "0": 1}, {"": 1}, {"": 1}, {"255": 1}, {"l2": 1, "distance": 1, "255": 1, "would": 1, "indicate": 1, "one": 1, "pixel": 1, "difference": 1}, {"l1": 1, "distance": 1, "represent": 1, "largest": 1, "absolute": 1, "difference": 1, "image": 1, "pixels": 1}, {"jittered": 2, "l2": 1, "distance": 2, "l1": 1, "": 11, "min": 1, "25": 1, "med": 1, "75": 1, "max": 1, "0": 2, "71": 1, "1": 4, "87": 1, "105": 1, "173": 1, "3": 1, "table": 1, "2": 1, "count": 1, "train": 1, "sample": 1, "mnist": 1, "qmnist": 1, "image": 1, "align": 1, "best": 1, "without": 1, "translation": 2, "pixel": 1}, {"0": 1, "pixels": 2, "": 4, "jitter": 1, "number": 1, "match": 2, "59853": 1, "1": 1, "147": 1, "table": 1, "3": 1, "misclassification": 1, "rat": 1, "lenet5": 1, "convolutional": 1, "network": 1, "train": 2, "mnist": 3, "qmnist": 3, "set": 3, "test": 5, "10k": 1, "examples": 2, "50k": 1, "remain": 1}, {"test": 1, "train": 2, "mnist": 3, "qmnist": 2, "": 7, "qmnist10k": 1, "qmnist50k": 1, "082": 1, "02": 4, "081": 2, "080": 1, "108": 2, "01": 2, "table": 1, "1": 1, "give": 1, "quartiles": 1, "l2": 1, "distance": 2, "l1": 1, "image": 1, "account": 1, "occasional": 1, "single": 1, "pixel": 1, "shift": 1}, {"l2": 1, "distance": 1, "255": 1, "would": 1, "indicate": 1, "full": 1, "pixel": 1, "difference": 1}, {"l1": 1, "distance": 1, "represent": 1, "largest": 1, "difference": 1, "image": 1, "pixels": 1, "express": 1, "integers": 1, "range": 1, "0": 1, "": 1}, {"": 1}, {"": 1}, {"255": 1}, {"order": 1, "verify": 1, "reconstruction": 1, "quality": 1, "train": 1, "variant": 1, "lenet5": 1, "network": 1, "describe": 1, "le": 1, "cun": 1, "et": 1, "al": 1}, {"1998": 1}, {"original": 1, "implementation": 1, "still": 1, "available": 1, "demonstration": 1, "lush": 1, "codebase": 1}, {"lush": 1, "bottou": 2, "lecun": 1, "2001": 1, "descend": 1, "sn": 1, "neural": 1, "network": 1, "software": 1, "le": 1, "cun": 1, "1988": 1, "att": 1, "bell": 1, "laboratories": 1, "variants": 1, "developped": 1, "nineties": 1}, {"particular": 1, "variant": 1, "lenet5": 1, "omit": 1, "final": 1, "euclidean": 1, "layer": 1, "describe": 1, "le": 1, "cun": 1, "et": 1, "al": 1, "1998": 1, "without": 1, "incur": 1, "performance": 1, "penalty": 1}, {"follow": 1, "pattern": 1, "set": 2, "original": 1, "implementation": 1, "train": 1, "protocol": 1, "consist": 1, "three": 1, "10": 4, "epochs": 1, "global": 1, "stepsizes": 1, "4": 1, "": 3, "5": 1, "6": 1}, {"set": 1, "start": 1, "estimate": 1, "diagonal": 1, "hessian": 1}, {"perweight": 1, "stepsizes": 1, "compute": 1, "divide": 1, "global": 1, "stepsize": 1, "estimate": 1, "curvature": 1, "plus": 1, "002": 1}, {"table": 1, "3": 1, "report": 1, "insignificant": 1, "differences": 1, "one": 1, "train": 2, "mnist": 2, "qmnist": 2, "set": 3, "test": 3, "match": 1, "part": 1}, {"hand": 1, "observe": 1, "substantial": 1, "difference": 1, "test": 3, "remain": 1, "part": 1, "qmnist": 1, "set": 1, "reconstructions": 1, "lose": 1, "mnist": 1, "digits": 1}, {"discrepancies": 1, "discuss": 1, "precisely": 1, "section": 1, "3": 1}, {"23": 1, "": 2, "mnist": 2, "trivia": 1, "reconstruction": 1, "effort": 1, "allow": 1, "us": 1, "uncover": 1, "lot": 1, "previously": 1, "unreported": 1, "facts": 1}, {"1": 1}, {"exactly": 1, "three": 1, "duplicate": 1, "digits": 1, "entire": 1, "nist": 1, "handwritten": 1, "character": 1, "collection": 1}, {"one": 1, "fall": 1, "segment": 1, "use": 1, "generate": 1, "mnist": 2, "remove": 1, "author": 1}, {"2": 1}, {"first": 1, "5001": 1, "image": 1, "mnist": 1, "test": 1, "set": 1, "seem": 1, "randomly": 1, "pick": 1, "write": 1, "writers": 1, "23502599": 1, "high": 1, "school": 1, "students": 1}, {"next": 1, "4999": 1, "image": 2, "consecutive": 1, "nist": 1, "3500039998": 1, "order": 1, "write": 1, "48": 1, "census": 1, "bureau": 1, "employees": 1, "writers": 1, "326373": 1, "show": 1, "figure": 1, "5": 1}, {"although": 1, "small": 1, "number": 1, "could": 1, "make": 1, "us": 1, "fear": 1, "statistical": 1, "significance": 1, "comparatively": 1, "clean": 1, "image": 1, "contribute": 1, "little": 1, "total": 1, "test": 1, "error": 1}, {"4": 1, "": 1, "3": 1}, {"evennumbered": 1, "image": 1, "among": 1, "58100": 1, "first": 1, "mnist": 1, "train": 1, "set": 1, "sample": 1, "exactly": 1, "match": 1, "digits": 1, "write": 1, "writers": 1, "21002349": 1, "high": 1, "school": 1, "students": 1, "random": 1, "order": 1}, {"remain": 1, "image": 2, "nist": 1, "0": 1, "30949": 1, "order": 1}, {"begin": 1, "sequence": 1, "visible": 1, "figure": 1, "2": 1}, {"therefore": 1, "half": 1, "image": 2, "find": 1, "typical": 1, "minibatch": 1, "consecutive": 1, "mnist": 1, "train": 1, "likely": 1, "write": 1, "writer": 1}, {"recommend": 1, "shuffle": 1, "train": 1, "set": 1, "assemble": 1, "minibatches": 1}, {"4": 1}, {"round": 1, "error": 1, "final": 1, "center": 1, "28x28": 1, "mnist": 1, "image": 1}, {"average": 1, "center": 2, "mass": 1, "mnist": 1, "digits": 1, "fact": 1, "locate": 1, "half": 1, "pixel": 1, "away": 1, "geometrical": 1, "image": 1}, {"important": 1, "train": 1, "correctly": 1, "center": 1, "image": 1, "yield": 1, "substantially": 1, "worse": 1, "performance": 1, "standard": 1, "mnist": 1, "test": 1, "set": 1}, {"5": 1}, {"slight": 1, "defect": 1, "mnist": 1, "resampling": 1, "code": 1, "generate": 1, "low": 1, "amplitude": 1, "periodic": 1, "pattern": 1, "dark": 1, "areas": 1, "thick": 1, "character": 1}, {"pattern": 2, "illustrate": 1, "figure": 1, "3": 1, "trace": 1, "099": 1, "fudge": 1, "factor": 1, "still": 1, "visible": 1, "lush": 1, "legacy": 1, "code5": 1, "since": 1, "period": 1, "depend": 1, "size": 2, "input": 1, "image": 2, "pass": 1, "resampling": 2, "code": 2, "able": 1, "determine": 1, "small": 1, "nist": 1, "upsampled": 1, "directly": 1, "call": 1, "first": 1, "double": 1, "resolution": 1, "downsampling": 1, "20x20": 1}, {"6": 1}, {"convert": 1, "continuousvalued": 1, "pixels": 2, "subsampled": 1, "image": 1, "integervalued": 1, "delicate": 1}, {"code": 1, "linearly": 1, "map": 1, "range": 1, "observe": 1, "image": 1, "interval": 1, "002550": 1, "round": 1, "closest": 1, "integer": 1}, {"compare": 1, "pixel": 1, "histograms": 1, "see": 1, "figure": 1, "4": 1, "reveal": 1, "mnist": 1, "substantially": 1, "pixels": 2, "value": 2, "128": 1, "less": 1, "255": 1}, {"could": 1, "think": 1, "plausibly": 1, "simple": 1, "algorithm": 1, "compatible": 1, "observation": 1}, {"3": 1, "": 2, "generalization": 1, "experiment": 1, "section": 1, "take": 1, "advantage": 1, "reconstruction": 1, "lose": 1, "50000": 1, "test": 1, "sample": 1, "revisit": 1, "mnist": 1, "performance": 1, "result": 1, "report": 1, "last": 1, "twentyfive": 1, "years": 1}, {"recht": 1, "et": 1, "al": 1}, {"2018": 1, "2019": 1, "perform": 1, "similar": 1, "study": 1, "cifar10": 1, "imagenet": 1, "datasets": 1, "identify": 1, "interest": 1, "trend": 1}, {"however": 1, "also": 1, "explain": 1, "cannot": 1, "fully": 1, "ascertain": 1, "closely": 1, "distribution": 2, "reconstruct": 2, "dataset": 3, "match": 1, "original": 2, "raise": 1, "possibility": 1, "substantially": 1, "harder": 1}, {"publish": 1, "mnist": 1, "test": 1, "set": 2, "subsampled": 1, "larger": 1, "much": 1, "tighter": 1, "control": 1, "data": 1, "distribution": 1, "confidently": 1, "confirm": 1, "find": 1}, {"mnist": 1, "test": 1, "error": 2, "rat": 1, "usually": 1, "low": 1, "start": 1, "careful": 1, "discussion": 1, "computation": 1, "confidence": 1, "intervals": 1, "statistical": 1, "significance": 1, "comparisons": 1, "context": 1, "repeat": 1, "experiment": 1}, {"report": 1, "mnist": 1, "result": 1, "several": 2, "methods": 1, "knearest": 1, "neightbors": 1, "knn": 1, "support": 1, "vector": 1, "machine": 1, "svm": 1, "multilayer": 1, "perceptrons": 1, "mlp": 1, "flavor": 1, "convolutional": 1, "network": 1, "cnn": 1}, {"31": 1, "": 11, "confidence": 5, "intervals": 3, "since": 1, "want": 1, "know": 1, "whether": 1, "actual": 1, "performance": 2, "learn": 1, "system": 1, "differ": 1, "estimate": 1, "use": 2, "overuse": 1, "test": 1, "set": 1, "runofthemill": 1, "report": 2, "work": 1, "obtain": 1, "classic": 1, "wald": 1, "method": 1, "observe": 1, "n1": 2, "misclassifications": 1, "n": 3, "independent": 1, "sample": 1, "error": 1, "rate": 1, "1": 4, "r": 1, "z": 2, "p": 1, "2": 2, "erfc": 1, "approximately": 1, "equal": 1, "95": 1, "interval": 1}, {"instance": 1, "error": 2, "rate": 2, "close": 1, "10": 1, "measure": 1, "usual": 1, "10000": 1, "test": 1, "example": 1, "report": 1, "1": 1, "": 2, "02": 1, "100": 1, "20": 1, "misclassifications": 1}, {"approach": 1, "widely": 1, "use": 2, "despite": 1, "fact": 1, "hold": 1, "single": 1, "test": 1, "set": 1, "rely": 1, "imperfect": 1, "central": 1, "limit": 1, "approximation": 1}, {"simplest": 1, "way": 1, "account": 1, "repeat": 1, "use": 1, "test": 1, "set": 1, "bonferroni": 2, "correction": 1, "1936": 1, "divide": 1, "": 4, "number": 1, "k": 1, "potential": 1, "experiment": 1, "simultaneously": 1, "define": 1, "5": 2, "see": 1, "httpstinyurlcomy5z7abyt": 1, "figure": 1, "3": 1, "reproduce": 1, "defect": 1, "original": 1, "resampling": 1, "code": 1, "create": 1, "low": 1, "amplitude": 1, "periodic": 1, "pattern": 1, "dark": 1, "areas": 1, "thick": 1, "character": 1}, {"005": 1, "": 8, "001": 1, "0005": 1, "0001": 1, "00005": 1, "00001": 1, "50": 1, "100": 1, "150": 1, "200": 1, "250": 1, "figure": 1, "4": 1, "histogram": 1, "pixel": 1, "value": 1, "range": 1, "1255": 1, "mnist": 1, "red": 1, "dot": 1, "qmnist": 1, "blue": 1, "line": 1, "train": 1, "set": 1}, {"logarithmic": 1, "scale": 1}, {"figure": 1, "5": 1, "histogram": 1, "writer": 2, "ids": 1, "number": 1, "digits": 1, "write": 1, "mnist": 2, "train": 1, "test": 2, "10k": 1, "qmnist": 1, "50k": 1, "set": 1}, {"perform": 1, "measurement": 1}, {"although": 1, "relax": 1, "simultaneity": 1, "constraint": 1, "progressively": 1, "require": 1, "apparatus": 1, "statistical": 1, "learn": 1, "theory": 1, "vapnik": 1, "1982": 1, "63": 1, "correction": 1, "still": 1, "take": 1, "form": 1, "divisor": 1, "k": 1, "apply": 1, "confidence": 1, "level": 1, "": 1}, {"asymptotic": 1, "properties": 1, "erfc": 1, "function": 1, "width": 1, "actual": 1, "confidence": 1, "intervals": 1, "essentially": 1, "grow": 1, "like": 1, "logk": 1}, {"order": 1, "complete": 1, "picture": 1, "one": 1, "also": 1, "need": 1, "take": 1, "account": 1, "benefit": 1, "use": 1, "test": 1, "set": 1}, {"ordinary": 1, "confidence": 1, "intervals": 1, "overly": 1, "pessimistic": 1, "merely": 1, "want": 1, "know": 1, "whether": 1, "first": 1, "classifier": 2, "error": 2, "rate": 2, "1": 1, "": 2, "n1": 1, "n": 2, "worse": 1, "second": 1, "2": 1, "n2": 1}, {"error": 1, "rat": 1, "measure": 1, "test": 1, "sample": 1, "instead": 1, "rely": 1, "pair": 1, "argument": 1, "first": 2, "classifier": 3, "consider": 1, "worse": 1, "confidence": 2, "1": 3, "": 13, "2": 4, "n12": 3, "n21": 3, "n": 2, "z": 2, "p": 2, "represent": 1, "count": 1, "examples": 1, "misclassified": 1, "second": 1, "converse": 1, "erfc": 1, "approximately": 1, "17": 1, "95": 1}, {"instance": 1, "four": 1, "additional": 1, "misclassifications": 1, "10000": 1, "examples": 1, "sufficient": 1, "make": 1, "determination": 1}, {"correspond": 1, "difference": 1, "error": 2, "rate": 1, "004": 1, "roughly": 1, "ten": 1, "time": 1, "smaller": 1, "would": 1, "need": 1, "observe": 1, "disjoint": 1, "bar": 1, "1": 1}, {"advantage": 1, "become": 1, "significant": 1, "combine": 1, "bonferronistyle": 1, "correction": 1, "k": 2, "pairwise": 2, "comparisons": 3, "remain": 2, "simultaneously": 1, "6": 1, "": 29, "valid": 2, "confidence": 2, "1": 3, "satisfy": 1, "n12": 4, "n21": 4, "p": 2, "2": 3, "erfc": 1, "instance": 1, "realistic": 1, "situation": 1, "n": 1, "10000": 1, "n1": 2, "200": 1, "40": 1, "10": 1, "n2": 1, "170": 1, "conclusion": 1, "classifier": 2, "worse": 1, "95": 1, "long": 1, "part": 1, "series": 1, "k4545": 1}, {"contrast": 1, "merely": 1, "k50": 1, "experiment": 1, "95": 1, "confidence": 1, "interval": 1, "absolute": 1, "error": 2, "rate": 2, "classifier": 2, "1": 1, "already": 1, "2": 2, "": 1, "05": 1, "large": 1, "distinguish": 1}, {"therefore": 1, "expect": 1, "repeat": 1, "model": 1, "selection": 1, "test": 5, "set": 5, "lead": 1, "decisions": 1, "remain": 1, "valid": 1, "far": 1, "longer": 1, "correspond": 1, "absolute": 1, "error": 1, "rates6": 1, "32": 1, "": 2, "result": 2, "report": 1, "use": 1, "two": 1, "train": 3, "namely": 2, "mnist": 5, "qmnist": 1, "reconstructions": 1, "digits": 2, "three": 1, "official": 2, "10000": 1, "sample": 2, "reconstruction": 2, "qmnist10k": 1, "lose": 1, "50000": 1, "qmnist50k": 1}, {"use": 1, "name": 1, "tmtm": 1, "tmtq10": 1, "tmtq50": 1, "identify": 1, "result": 1, "measure": 1, "three": 1, "test": 1, "set": 2, "train": 2, "mnist": 1}, {"similarly": 1, "use": 1, "name": 1, "tqtm": 1, "tqtq10": 1, "tqtq50": 1, "result": 1, "obtain": 1, "train": 2, "qmnist": 1, "set": 2, "test": 2, "three": 1}, {"none": 1, "result": 1, "involve": 1, "data": 1, "augmentation": 1, "preprocessing": 1, "step": 1, "deskewing": 1, "noise": 1, "removal": 1, "blur": 1, "jittering": 1, "elastic": 1, "deformations": 1, "etc": 1}, {"figure": 1, "6": 1, "leave": 1, "plot": 1, "report": 1, "test": 1, "error": 1, "rat": 1, "obtain": 1, "knn": 1, "various": 1, "value": 1, "parameter": 1, "k": 1, "use": 1, "mnist": 1, "train": 1, "set": 1, "reference": 1, "point": 1}, {"qmnist50k": 1, "result": 1, "slightly": 1, "worse": 1, "within": 1, "confidence": 1, "intervals": 1}, {"best": 2, "k": 2, "determine": 1, "mnist": 1, "also": 1, "qmnist50k": 1}, {"figure": 1, "6": 1, "right": 1, "plot": 1, "report": 1, "similar": 1, "result": 1, "conclusions": 1, "use": 1, "qmnist": 1, "train": 1, "set": 1, "reference": 1, "point": 1}, {"figure": 1, "7": 1, "report": 1, "test": 1, "error": 1, "rat": 1, "obtain": 1, "rbf": 1, "kernel": 1, "svms": 1, "train": 2, "mnist": 1, "set": 1, "various": 1, "value": 1, "hyperparameters": 1, "c": 1, "g": 1, "qmnist50": 1, "result": 1, "consistently": 1, "higher": 1, "still": 1, "fall": 1, "within": 1, "confidence": 1, "intervals": 1, "except": 1, "maybe": 1, "misregularized": 1, "model": 1}, {"hyperparameters": 1, "achieve": 2, "best": 2, "mnist": 1, "performance": 2, "also": 1, "qmnist50k": 1}, {"figure": 1, "8": 1, "leave": 1, "plot": 1, "provide": 1, "similar": 1, "result": 1, "single": 1, "hide": 2, "layer": 2, "multilayer": 1, "network": 1, "various": 1, "size": 1, "average": 1, "five": 1, "run": 1}, {"qmnist50k": 1, "result": 2, "appear": 1, "consistently": 1, "worse": 1, "mnist": 1, "test": 1, "set": 1}, {"one": 1, "hand": 1, "best": 2, "qmnist50k": 1, "performance": 1, "achieve": 2, "network": 2, "1100": 1, "hide": 2, "units": 2, "whereas": 1, "mnist": 1, "test": 1, "error": 1, "700": 1}, {"hand": 1, "network": 1, "300": 1, "1100": 1, "hide": 1, "units": 1, "perform": 1, "similarly": 1, "mnist": 1, "qmnist50": 1, "see": 1, "plot": 1}, {"95": 1, "confidence": 1, "interval": 1, "pair": 1, "test": 2, "representative": 1, "run": 1, "reveal": 1, "statistically": 1, "significant": 1, "differences": 1, "mnist": 1, "performances": 1, "network": 1}, {"point": 1, "figure": 1, "8": 1, "right": 1, "plot": 1, "give": 1, "mnist": 1, "qmnist50k": 1, "test": 1, "error": 1, "rat": 1, "one": 1, "mlp": 1, "experiment": 1}, {"plot": 1, "include": 1, "experiment": 1, "several": 2, "hide": 1, "layer": 1, "size": 2, "also": 1, "minibatch": 1, "learn": 1, "rat": 1}, {"able": 1, "replicate": 1, "report": 1, "16": 1, "error": 1, "rate": 1, "le": 1, "cun": 1, "et": 1, "al": 1}, {"1998": 1, "use": 1, "minibatches": 1, "five": 1, "less": 1, "examples": 1}, {"finally": 1, "figure": 1, "9": 1, "summarize": 1, "experiment": 1, "report": 1}, {"also": 1, "include": 1, "several": 1, "flavor": 1, "convolutional": 1, "network": 1, "lenet5": 1, "result": 2, "already": 1, "present": 1, "table": 1, "3": 1, "vgg11": 1, "simonyan": 1, "zisserman": 1, "2014": 1, "resnet18": 1, "et": 1, "al": 1, "2016": 1, "representative": 1, "modern": 1, "cnn": 1, "architectures": 1, "currently": 1, "popular": 1, "computer": 1, "vision": 1}, {"also": 1, "report": 1, "result": 1, "obtain": 1, "use": 1, "four": 1, "model": 3, "tfkr": 1, "mnist": 2, "challenge7": 1, "tfkra8": 1, "ensemble": 1, "two": 1, "vggand": 1, "one": 1, "resnetlike": 1, "train": 2, "augment": 1, "version": 1, "set": 1}, {"model": 1, "6": 1, "": 1, "see": 1, "feldman": 1, "et": 1, "al": 1, "2019": 1, "different": 1, "perspective": 1, "issue": 1}, {"httpsgithubcomhwalsukleehowfarcanwegowithmnist": 1, "8": 1, "tfkra": 1, "httpsgithubcomkhanrcmnist": 1, "7": 2, "": 2, "figure": 1, "6": 1, "knn": 1, "error": 1, "rat": 1, "various": 1, "value": 1, "k": 1, "use": 1, "either": 1, "mnist": 1, "leave": 1, "plot": 2, "qmnist": 1, "right": 1, "train": 1, "set": 1}, {"red": 1, "circle": 1, "test": 1, "mnist": 1}, {"blue": 1, "triangles": 1, "test": 1, "qmnist": 1, "counterpart": 1}, {"green": 1, "star": 1, "test": 2, "50000": 1, "new": 1, "qmnist": 1, "examples": 1}, {"figure": 2, "7": 1, "svm": 1, "error": 1, "rat": 1, "various": 1, "value": 1, "regularization": 1, "parameter": 2, "c": 1, "leave": 1, "plot": 2, "rbf": 1, "kernel": 1, "g": 1, "right": 1, "train": 2, "mnist": 1, "set": 1, "use": 1, "color": 1, "symbols": 1, "6": 1}, {"figure": 2, "8": 1, "leave": 1, "plot": 1, "mlp": 1, "error": 1, "rat": 1, "various": 1, "hide": 1, "layer": 1, "size": 1, "train": 1, "mnist": 1, "use": 1, "color": 1, "symbols": 1, "6": 1}, {"right": 1, "plot": 2, "scatter": 1, "compare": 1, "mnist": 1, "qmnist50k": 1, "test": 1, "errors": 1, "mlp": 1, "experiment": 1}, {"8": 1, "": 1, "figure": 1, "9": 1, "scatter": 1, "plot": 1, "compare": 1, "mnist": 2, "qmnist50k": 1, "test": 1, "performance": 1, "model": 1, "train": 1, "course": 1, "study": 1}, {"tfkrb9": 1, "": 2, "tfkrc10": 1, "tfkrd11": 1, "single": 1, "cnn": 1, "model": 1, "vary": 1, "architectures": 1}, {"scatter": 1, "plot": 1, "show": 1, "qmnist50": 1, "error": 1, "rat": 1, "consistently": 1, "slightly": 1, "higher": 1, "mnist": 1, "test": 1, "errors": 1}, {"however": 1, "plot": 1, "also": 1, "show": 1, "compare": 1, "mnist": 1, "test": 1, "set": 1, "performances": 2, "various": 1, "model": 1, "provide": 1, "near": 1, "perfect": 1, "rank": 1, "correspond": 1, "qmnist50k": 1}, {"particular": 1, "best": 2, "perform": 2, "model": 2, "mnist": 1, "tfkra": 1, "remain": 1, "qmnist50k": 1}, {"4": 1, "": 2, "conclusion": 1, "recreate": 1, "close": 1, "approximation": 1, "mnist": 1, "preprocessing": 1, "chain": 1}, {"track": 1, "mnist": 2, "digit": 1, "nist": 1, "source": 1, "image": 1, "associate": 1, "metadata": 1, "also": 1, "recreate": 1, "original": 1, "test": 1, "set": 1, "include": 1, "50000": 1, "sample": 1, "never": 1, "distribute": 1}, {"fresh": 1, "test": 2, "sample": 1, "allow": 1, "us": 1, "investigate": 1, "result": 1, "report": 1, "standard": 1, "set": 1, "suffer": 1, "repeat": 1, "experimentation": 1}, {"result": 1, "confirm": 1, "trend": 1, "observe": 1, "recht": 1, "et": 1, "al": 1}, {"2018": 1, "2019": 1, "albeit": 1, "different": 1, "dataset": 1, "substantially": 1, "control": 1, "setup": 1}, {"result": 1, "essentially": 1, "show": 1, "test": 1, "set": 1, "rot": 1, "problem": 1, "exist": 1, "far": 1, "less": 1, "severe": 1, "fear": 1}, {"although": 1, "repeat": 1, "usage": 1, "test": 1, "set": 1, "impact": 1, "absolute": 1, "performance": 1, "number": 1, "also": 1, "deliver": 1, "pair": 1, "advantage": 1, "help": 1, "model": 1, "selection": 1, "long": 1, "run": 1}, {"practice": 1, "suggest": 1, "shift": 1, "data": 1, "distribution": 1, "far": 1, "dangerous": 1, "overuse": 1, "adequately": 1, "distribute": 1, "test": 1, "set": 1}, {"9": 2, "": 3, "tfkrb": 1, "httpsgithubcombart99tensorflowtreemastermnist": 1, "tfkrc": 1, "httpsgithubcomchaesodnnstudy": 1, "11": 1, "tfkrd": 1, "httpsgithubcombyeongkijeongmostaccurablemnistkeras": 1, "10": 1, "acknowledgments": 1, "thank": 1, "chris": 1, "burges": 1, "corinna": 1, "cortes": 1, "yann": 1, "lecun": 1, "precious": 1, "information": 1, "able": 1, "share": 1, "us": 1, "birth": 1, "mnist": 1}, {"thank": 1, "larry": 1, "jackel": 1, "instigate": 1, "whole": 1, "mnist": 1, "project": 1, "comment": 1, "cold": 1, "case": 1}, {"thank": 1, "maithra": 1, "raghu": 1, "point": 1, "qmnist": 1, "could": 1, "use": 1, "corroborate": 1, "result": 1, "recht": 1, "et": 1, "al": 1}, {"2019": 1}, {"thank": 1, "ben": 1, "recht": 1, "ludwig": 1, "schmidt": 1, "roman": 1, "werpachowski": 1, "constructive": 1, "comment": 1}, {"reference": 1, "carlo": 1, "e": 1, "bonferroni": 1}, {"teoria": 1, "statistica": 1, "delle": 2, "classi": 1, "e": 1, "calcolo": 1, "probabilit": 1}, {"pubblicazioni": 1, "del": 1, "r": 1, "istituto": 1, "superiore": 1, "di": 2, "scienze": 1, "economiche": 1, "e": 1, "commerciali": 1, "firenze": 1}, {"libreria": 1, "internazionale": 1, "seeber": 1, "1936": 1}, {"lon": 1, "bottou": 1, "yann": 1, "le": 1, "cun": 1}, {"sn": 1, "simulator": 1, "connectionist": 1, "model": 1}, {"proceed": 1, "neuronimes": 1, "88": 1, "page": 1, "371382": 1, "nimes": 1, "france": 1, "1988": 1}, {"lon": 1, "bottou": 1, "yann": 1, "lecun": 1}, {"lush": 1, "reference": 1, "manual": 1}, {"httplushsfnetdoc": 1, "2001": 1}, {"lon": 1, "bottou": 1, "corinna": 1, "cortes": 1, "john": 1, "denker": 1, "harris": 1, "drucker": 1, "isabelle": 1, "guyon": 1, "lawrence": 1, "jackel": 1, "yann": 1, "le": 1, "cun": 1, "urs": 1, "muller": 1, "eduard": 1, "sckinger": 1, "patrice": 1, "simard": 1, "vladimir": 1, "vapnik": 1}, {"comparison": 1, "classifier": 1, "methods": 1, "case": 1, "study": 1, "handwritten": 1, "digit": 1, "recognition": 1}, {"proceed": 1, "12th": 1, "iapr": 1, "international": 1, "conference": 2, "pattern": 1, "recognition": 1, "b": 1, "computer": 1, "vision": 1, "": 1, "image": 1, "process": 1, "volume": 1, "2": 1, "page": 1, "7782": 1, "jerusalem": 1, "october": 1, "1994": 1}, {"ieee": 1}, {"vitaly": 1, "feldman": 1, "roy": 1, "frostig": 1, "moritz": 1, "hardt": 1}, {"advantage": 1, "multiple": 1, "class": 1, "reduce": 1, "overfitting": 1, "test": 1, "set": 1, "reuse": 1}, {"kamalika": 1, "chaudhuri": 1, "ruslan": 1, "salakhutdinov": 1, "editors": 1, "proceed": 2, "36th": 1, "international": 1, "conference": 1, "machine": 2, "learn": 2, "volume": 1, "97": 1, "research": 1, "page": 1, "18921900": 1}, {"pmlr": 1, "2019": 1}, {"patrick": 1, "j": 1, "grother": 1, "kayee": 1, "k": 1, "hanaoka": 1}, {"nist": 1, "special": 1, "database": 2, "19": 1, "handprinted": 1, "form": 1, "character": 1}, {"httpswwwnistgovsrdnistspecialdatabase19": 1, "1995": 1}, {"sd1": 1, "release": 1, "1990": 1, "sd3": 1, "sd7": 1, "1992": 1, "sd19": 2, "1995": 1, "2nd": 1, "edition": 1, "2016": 1}, {"kaiming": 1, "xiangyu": 1, "zhang": 1, "shaoqing": 1, "ren": 1, "jian": 1, "sun": 1}, {"deep": 1, "residual": 1, "learn": 1, "image": 1, "recognition": 1}, {"proceed": 1, "ieee": 1, "conference": 1, "computer": 1, "vision": 1, "pattern": 1, "recognition": 1, "page": 1, "770778": 1, "2016": 1}, {"yann": 1, "le": 1, "cun": 1, "lon": 1, "bottou": 1, "yoshua": 1, "bengio": 1, "patrick": 1, "haffner": 1}, {"gradient": 1, "base": 1, "learn": 1, "apply": 1, "document": 1, "recognition": 1}, {"proceed": 1, "ieee": 1, "861122782324": 1, "1998": 1}, {"yann": 1, "lecun": 1, "corinna": 1, "cortes": 1, "christopher": 1, "j": 1, "c": 1, "burges": 1}, {"mnist": 1, "database": 1, "handwritten": 1, "digits": 1}, {"httpyannlecuncomexdbmnist": 1, "1994": 1}, {"mnist": 1, "create": 1, "1994": 1, "release": 1, "1998": 1}, {"benjamin": 1, "recht": 1, "rebecca": 1, "roelofs": 1, "ludwig": 1, "schmidt": 1, "vaishaal": 1, "shankar": 1}, {"cifar10": 2, "classifiers": 1, "generalize": 1}, {"arxiv": 1, "preprint": 1, "arxiv180600451": 1, "2018": 1}, {"benjamin": 1, "recht": 1, "rebecca": 1, "roelofs": 1, "ludwig": 1, "schmidt": 1, "vaishaal": 1, "shankar": 1}, {"imagenet": 2, "classifiers": 1, "generalize": 1}, {"proceed": 1, "36th": 1, "international": 1, "conference": 1, "machine": 1, "learn": 1}, {"pmlr": 1, "2019": 1}, {"karen": 1, "simonyan": 1, "andrew": 1, "zisserman": 1}, {"deep": 1, "convolutional": 1, "network": 1, "largescale": 1, "image": 1, "recognition": 1}, {"arxiv": 1, "preprint": 1, "arxiv14091556": 1, "2014": 1}, {"v": 1, "n": 1, "vapnik": 1}, {"estimation": 1, "dependences": 1, "base": 1, "empirical": 1, "data": 1}, {"springer": 1, "series": 1, "statistics": 1}, {"springer": 1, "verlag": 1, "berlin": 1, "new": 1, "york": 1, "1982": 1}, {"10": 1}]